{"展览": [{"开始时间": "2024-04-12 - 2024-06-30", "名称": "上海·吉卜力工作室物语-沉浸式艺术展全球首站", "地点": "上海国际传媒港艺术中心", "具体时间范围": "2024-04-12 10:00:00", "最低票价": "88.0", "Link": "https://show.bilibili.com/platform/detail.html?id=83036", "Cover": "//i0.hdslb.com/bfs/openplatform/202403/aZoum5Hd1710472525792.jpeg"}, {"开始时间": "2024-05-25 - 2024-08-18", "名称": "上海·《宫西达也的绘本世界》", "地点": "合生汇", "具体时间范围": "2024-05-25 10:00:00", "最低票价": "88.0", "Link": "https://show.bilibili.com/platform/detail.html?id=86496", "Cover": "//i1.hdslb.com/bfs/openplatform/202405/aSUGj8i31716949002492.jpeg"}, {"开始时间": "2024-06-01 - 2024-06-30", "名称": "上海·秦潮觉醒沉浸式探索体验", "地点": "秦潮觉醒XR沉浸体验展", "具体时间范围": "2024-06-01 10:00:00", "最低票价": "不可售", "Link": "https://show.bilibili.com/platform/detail.html?id=85604", "Cover": "//i1.hdslb.com/bfs/openplatform/202405/Ll4BZQLw1715658305492.png"}, {"开始时间": "2024-06-08 - 2024-10-07", "名称": "上海·无穹-中国 航天沉浸艺术展", "地点": "上海喜玛拉雅美术馆", "具体时间范围": "2024-06-08 10:00:00", "最低票价": "78.0", "Link": "https://show.bilibili.com/platform/detail.html?id=86957", "Cover": "//i1.hdslb.com/bfs/openplatform/202406/Bus3lAnI1717558639134.jpeg"}, {"开始时间": "2024-06-15 - 2024-06-16", "名称": "上海·第二届环绕银河动漫游戏嘉年华·音你跃动", "地点": "PK西餐厅运动娱乐中心(普陀信泰中心店)", "具体时间范围": "2024-06-15 10:00:00", "最低票价": "78.0", "Link": "https://show.bilibili.com/platform/detail.html?id=86513", "Cover": "//i0.hdslb.com/bfs/openplatform/202405/Gk5tu5E41716866802069.jpeg"}, {"开始时间": "2024-06-16", "名称": "上海·宅舞联萌·随舞动漫派对（免费活动）", "地点": "百脑汇(漕溪北路旗舰店)", "具体时间范围": "2024-06-16 14:00:00", "最低票价": "22.33", "Link": "https://show.bilibili.com/platform/detail.html?id=85656", "Cover": "//i2.hdslb.com/bfs/openplatform/202405/NV0dnyhg1715755075562.jpeg"}, {"开始时间": "2024-06-21 - 2024-06-23", "名称": "上海·第一届触圈动漫(CQ)展", "地点": "静安国际科创社区云芯科创中心", "具体时间范围": "2024-06-21 14:00:00", "最低票价": "70.0", "Link": "https://show.bilibili.com/platform/detail.html?id=85312", "Cover": "//i0.hdslb.com/bfs/openplatform/202405/QPXgNO6X1715222404042.png"}, {"开始时间": "2024-06-22", "名称": "上海 星芒旋转 二次元团建狂欢日", "地点": "JUMP工坊", "具体时间范围": "2024-06-22 14:00:00", "最低票价": "60.0", "Link": "https://show.bilibili.com/platform/detail.html?id=86361", "Cover": "//i0.hdslb.com/bfs/openplatform/202405/NjWMqWjm1716797273634.jpeg"}, {"开始时间": "2024-06-22", "名称": "上海·622cp金婚only·沉沦", "地点": "丽丽薇里婚嫁礼堂婚宴(闵行店)", "具体时间范围": "2024-06-22 11:00:00", "最低票价": "68.0", "Link": "https://show.bilibili.com/platform/detail.html?id=85430", "Cover": "//i1.hdslb.com/bfs/openplatform/202405/vlXVjLBA1715077227390.png"}, {"开始时间": "2024-06-22", "名称": "上海·第五人格only", "地点": "竞梦元宇宙", "具体时间范围": "2024-06-22 10:00:00", "最低票价": "68.0", "Link": "https://show.bilibili.com/platform/detail.html?id=86971", "Cover": "//i1.hdslb.com/bfs/openplatform/202406/OOItNE0E1717592352095.png"}, {"开始时间": "2024-06-22 - 2024-06-23", "名称": "上海·COMICBLISS动漫嘉年华", "地点": "上海大世界", "具体时间范围": "2024-06-22 09:30:00", "最低票价": "68.0", "Link": "https://show.bilibili.com/platform/detail.html?id=86901", "Cover": "//i1.hdslb.com/bfs/openplatform/202406/KQjSSavY1717558632149.jpeg"}, {"开始时间": "2024-06-22 - 2024-06-23", "名称": "上海·第八届Redamancy动漫游戏嘉年华", "地点": "环球港上海世嘉都市乐园", "具体时间范围": "2024-06-22 10:00:00", "最低票价": "60.0", "Link": "https://show.bilibili.com/platform/detail.html?id=84635", "Cover": "//i2.hdslb.com/bfs/openplatform/202404/EadsJBh41713193501329.png"}, {"开始时间": "2024-06-22 - 2024-06-23", "名称": "上海·第六十二届燃梦星辰动漫嘉年华", "地点": "尚优里·乐坊生活广场", "具体时间范围": "2024-06-22 10:00:00", "最低票价": "58.8", "Link": "https://show.bilibili.com/platform/detail.html?id=85751", "Cover": "//i0.hdslb.com/bfs/openplatform/202405/lMjgV8wr1715842872181.jpeg"}, {"开始时间": "2024-06-22 - 2024-06-23", "名称": "上海·运动番only", "地点": "中成智谷", "具体时间范围": "2024-06-22 10:00:00", "最低票价": "89.0", "Link": "https://show.bilibili.com/platform/detail.html?id=87122", "Cover": "//i0.hdslb.com/bfs/openplatform/202406/Dhx52mWP1717689592171.jpeg"}, {"开始时间": "2024-06-23", "名称": "上海·原神×星穹铁道ONLY", "地点": "竞梦元宇宙", "具体时间范围": "2024-06-23 10:00:00", "最低票价": "68.0", "Link": "https://show.bilibili.com/platform/detail.html?id=87157", "Cover": "//i2.hdslb.com/bfs/openplatform/202406/imNmTcWA1718078981607.png"}, {"开始时间": "2024-06-29", "名称": "上海·咒术回战only（取消）", "地点": "云海大厦", "具体时间范围": "2024-06-29 10:00:00", "最低票价": "不可售", "Link": "https://show.bilibili.com/platform/detail.html?id=85055", "Cover": "//i0.hdslb.com/bfs/openplatform/202404/QeHd0lP91714108380981.png"}, {"开始时间": "2024-06-29", "名称": "上海·第六十三届燃梦星辰动漫嘉年华", "地点": "佘山·旭辉里", "具体时间范围": "2024-06-29 14:00:00", "最低票价": "58.8", "Link": "https://show.bilibili.com/platform/detail.html?id=85231", "Cover": "//i2.hdslb.com/bfs/openplatform/202406/Tx1g80PC1717667546414.jpeg"}, {"开始时间": "2024-06-29", "名称": "上海·葬送的芙莉莲ONLY", "地点": "上海宝丰联大酒店", "具体时间范围": "2024-06-29 10:00:00", "最低票价": "65.0", "Link": "https://show.bilibili.com/platform/detail.html?id=85193", "Cover": "//i2.hdslb.com/bfs/openplatform/202404/VIM2lfxY1714361685906.jpeg"}, {"开始时间": "2024-06-29 - 2024-06-30", "名称": "上海·cdc动漫展", "地点": "JUMP工坊", "具体时间范围": "2024-06-29 10:00:00", "最低票价": "60.0", "Link": "https://show.bilibili.com/platform/detail.html?id=85110", "Cover": "//i2.hdslb.com/bfs/openplatform/202405/RMpaP6sF1714725969882.jpeg"}, {"开始时间": "2024-06-29 - 2024-06-30", "名称": "上海·创世次元动漫游戏嘉年华3.0", "地点": "轮客行轮滑馆(普陀店)", "具体时间范围": "2024-06-29 10:00:00", "最低票价": "58.0", "Link": "https://show.bilibili.com/platform/detail.html?id=86506", "Cover": "//i2.hdslb.com/bfs/openplatform/202405/Clkfdwic1716894666596.jpeg"}, {"开始时间": "2024-06-29 - 2024-06-30", "名称": "上海·第十届Redamancy动漫游戏嘉年华", "地点": "上海JOYPOLIS世嘉都市乐园", "具体时间范围": "2024-06-29 10:00:00", "最低票价": "60.0", "Link": "https://show.bilibili.com/platform/detail.html?id=87334", "Cover": "//i0.hdslb.com/bfs/openplatform/202406/CJQAn6r81718289624171.png"}, {"开始时间": "2024-06-30", "名称": "上海 星芒旋转 anikura动漫嘉年华", "地点": "JUMP工坊", "具体时间范围": "2024-06-30 17:00:00", "最低票价": "60.0", "Link": "https://show.bilibili.com/platform/detail.html?id=86357", "Cover": "//i2.hdslb.com/bfs/openplatform/202405/RAjlTt6f1716788945862.jpeg"}, {"开始时间": "2024-07-05 - 2024-07-06", "名称": "上海·第三届GSCG动漫节", "地点": "上海大世界", "具体时间范围": "2024-07-05 10:00:00", "最低票价": "75.0", "Link": "https://show.bilibili.com/platform/detail.html?id=86561", "Cover": "//i1.hdslb.com/bfs/openplatform/202405/p5iDI2Mp1717031467789.png"}, {"开始时间": "2024-07-05 - 2024-07-07", "名称": "上海·NW新界动漫游戏展2.0", "地点": "月星家居", "具体时间范围": "2024-07-05 10:00:00", "最低票价": "59.0", "Link": "https://show.bilibili.com/platform/detail.html?id=83923", "Cover": "//i1.hdslb.com/bfs/openplatform/202404/nUixyAy21712605861917.jpeg"}, {"开始时间": "2024-07-06", "名称": "上海·全职猎人ONLY2.0 · 友客鑫拍卖会", "地点": "交运智慧湾科创园25号楼", "具体时间范围": "2024-07-06 10:00:00", "最低票价": "89.0", "Link": "https://show.bilibili.com/platform/detail.html?id=87214", "Cover": "//i0.hdslb.com/bfs/openplatform/202406/Nq3CyukM1718174450980.jpeg"}, {"开始时间": "2024-07-06", "名称": "上海·创世次元动漫游戏嘉年华4.0", "地点": "轮客行轮滑馆(普陀店)", "具体时间范围": "2024-07-06 10:00:00", "最低票价": "58.0", "Link": "https://show.bilibili.com/platform/detail.html?id=86339", "Cover": "//i0.hdslb.com/bfs/openplatform/202406/4xvoJEpz1718353272334.jpeg"}, {"开始时间": "2024-07-06", "名称": "上海·第五人格ONLY3.0", "地点": "诺宝中心酒店", "具体时间范围": "2024-07-06 10:00:00", "最低票价": "60.0", "Link": "https://show.bilibili.com/platform/detail.html?id=86058", "Cover": "//i2.hdslb.com/bfs/openplatform/202405/b9vpuu711716280652600.jpeg"}, {"开始时间": "2024-07-06 - 2024-07-07", "名称": "上海·坏孩纸物语の第45届动漫节之俞伯牙篇", "地点": "徐汇日月光中心", "具体时间范围": "2024-07-06 13:00:00", "最低票价": "55.6", "Link": "https://show.bilibili.com/platform/detail.html?id=86330", "Cover": "//i0.hdslb.com/bfs/openplatform/202405/us2hihO11716292063340.png"}, {"开始时间": "2024-07-06 - 2024-07-08", "名称": "上海·2024圣杯战争（取消）", "地点": "星零界", "具体时间范围": "2024-07-06 11:00:00", "最低票价": "不可售", "Link": "https://show.bilibili.com/platform/detail.html?id=85209", "Cover": "//i2.hdslb.com/bfs/openplatform/202405/P8ulUjVk1715743291864.jpeg"}, {"开始时间": "2024-07-12 - 2024-07-14", "名称": "上海·BilibiliWorld 2024", "地点": "上海国家会展中心", "具体时间范围": "2024-07-12 08:30:00", "最低票价": "不可售", "Link": "https://show.bilibili.com/platform/detail.html?id=85939", "Cover": "//i2.hdslb.com/bfs/openplatform/202406/k0Telb2o1717492841341.jpeg"}, {"开始时间": "2024-07-12 - 2024-07-14", "名称": "上海·魔都COS Voice暑假漫展", "地点": "月星家居", "具体时间范围": "2024-07-12 10:00:00", "最低票价": "49.0", "Link": "https://show.bilibili.com/platform/detail.html?id=84008", "Cover": "//i2.hdslb.com/bfs/openplatform/202404/jldYwFXi1712678080397.jpeg"}, {"开始时间": "2024-07-13", "名称": "上海·太中only", "地点": "诺宝中心酒店", "具体时间范围": "2024-07-13 10:00:00", "最低票价": "已售罄", "Link": "https://show.bilibili.com/platform/detail.html?id=84763", "Cover": "//i0.hdslb.com/bfs/openplatform/202404/SHjjt67q1713842062371.jpeg"}, {"开始时间": "2024-07-13", "名称": "上海·恋与深空only【女生专场】", "地点": "竞梦元宇宙", "具体时间范围": "2024-07-13 11:00:00", "最低票价": "88.0", "Link": "https://show.bilibili.com/platform/detail.html?id=87346", "Cover": "//i2.hdslb.com/bfs/openplatform/202406/vaE8H0CC1718081128645.jpeg"}, {"开始时间": "2024-07-13 - 2024-07-14", "名称": "上海·coser动漫展", "地点": "JUMP工坊", "具体时间范围": "2024-07-13 10:00:00", "最低票价": "60.0", "Link": "https://show.bilibili.com/platform/detail.html?id=87347", "Cover": "//i2.hdslb.com/bfs/openplatform/202406/gQC62xhm1718287366020.jpeg"}, {"开始时间": "2024-07-13 - 2024-07-14", "名称": "上海·坏孩纸物语の第47届动漫节之钟子期篇", "地点": "徐汇日月光中心", "具体时间范围": "2024-07-13 13:00:00", "最低票价": "56.9", "Link": "https://show.bilibili.com/platform/detail.html?id=86328", "Cover": "//i1.hdslb.com/bfs/openplatform/202405/7OYHZx0z1716292227567.png"}, {"开始时间": "2024-07-13 - 2024-07-14", "名称": "上海·第五届燃梦BACG PRO动漫嘉年华·我们在燃梦相遇吧！", "地点": "万达汽车乐园(青浦万达茂店)", "具体时间范围": "2024-07-13 11:00:00", "最低票价": "65.8", "Link": "https://show.bilibili.com/platform/detail.html?id=85235", "Cover": "//i2.hdslb.com/bfs/openplatform/202405/A9VkjJzh1715108077210.jpeg"}, {"开始时间": "2024-07-13 - 2024-07-14", "名称": "上海·第十三届ACBC动漫盛典（免费活动）", "地点": "LALA STATION上海莲花路店", "具体时间范围": "2024-07-13 10:00:00", "最低票价": "80.0", "Link": "https://show.bilibili.com/platform/detail.html?id=87158", "Cover": "//i1.hdslb.com/bfs/openplatform/202406/sYfCPdla1718084897256.jpeg"}, {"开始时间": "2024-07-14", "名称": "上海·囚鸢代号鸢Only【女生专场】", "地点": "竞梦元宇宙", "具体时间范围": "2024-07-14 11:00:00", "最低票价": "88.0", "Link": "https://show.bilibili.com/platform/detail.html?id=87331", "Cover": "//i1.hdslb.com/bfs/openplatform/202406/e053lkLC1718164512192.jpeg"}, {"开始时间": "2024-07-20", "名称": "上海·BanG Dream！ONLY3", "地点": "交运智慧湾科创园25号楼", "具体时间范围": "2024-07-20 10:00:00", "最低票价": "78.0", "Link": "https://show.bilibili.com/platform/detail.html?id=87304", "Cover": "//i2.hdslb.com/bfs/openplatform/202406/wPmKJQDs1718182986843.jpeg"}, {"开始时间": "2024-07-20", "名称": "上海·创世次元动漫游戏嘉年华7.0", "地点": "七宝万科广场", "具体时间范围": "2024-07-20 10:00:00", "最低票价": "58.0", "Link": "https://show.bilibili.com/platform/detail.html?id=86344", "Cover": "//i1.hdslb.com/bfs/openplatform/202405/drK8Z2DU1716735561023.jpeg"}, {"开始时间": "2024-07-20 - 2024-07-21", "名称": "上海·LookLook动漫嘉年华2th", "地点": "上海国际短视频中心", "具体时间范围": "2024-07-20 10:00:00", "最低票价": "29.9", "Link": "https://show.bilibili.com/platform/detail.html?id=87169", "Cover": "//i0.hdslb.com/bfs/openplatform/202406/EGJoo1VF1718094234619.png"}, {"开始时间": "2024-07-20 - 2024-07-21", "名称": "上海·第九届Redamancy动漫游戏嘉年华", "地点": "上海环球港", "具体时间范围": "2024-07-20 10:00:00", "最低票价": "60.0", "Link": "https://show.bilibili.com/platform/detail.html?id=84637", "Cover": "//i1.hdslb.com/bfs/openplatform/202404/hWLkXqwM1713194236349.png"}, {"开始时间": "2024-08-03", "名称": "上海·LOVELIVE ONLY", "地点": "JUMP工坊", "具体时间范围": "2024-08-03 14:00:00", "最低票价": "60.0", "Link": "https://show.bilibili.com/platform/detail.html?id=86711", "Cover": "//i2.hdslb.com/bfs/openplatform/202405/bllJHQFL1716983812432.jpeg"}, {"开始时间": "2024-08-04", "名称": "上海·赛马娘ONLY·星夜天航", "地点": "诺宝中心酒店", "具体时间范围": "2024-08-04 10:00:00", "最低票价": "80.0", "Link": "https://show.bilibili.com/platform/detail.html?id=87117", "Cover": "//i2.hdslb.com/bfs/openplatform/202406/bdPnwqoq1717659799773.jpeg"}, {"开始时间": "2024-08-10", "名称": "上海·创世次元动漫游戏嘉年华8.0", "地点": "七宝万科广场", "具体时间范围": "2024-08-10 10:00:00", "最低票价": "58.0", "Link": "https://show.bilibili.com/platform/detail.html?id=86337", "Cover": "//i1.hdslb.com/bfs/openplatform/202405/MryCBK6p1716736927373.jpeg"}, {"开始时间": "2024-08-11", "名称": "上海·KigOnly01·Kigurumi", "地点": "上海宝丰联大酒店", "具体时间范围": "2024-08-11 10:00:00", "最低票价": "不可售", "Link": "https://show.bilibili.com/platform/detail.html?id=85291", "Cover": "//i1.hdslb.com/bfs/openplatform/202404/GgqdW89w1714031044427.jpeg"}, {"开始时间": "2024-08-17", "名称": "上海·创世次元动漫游戏嘉年华9.0", "地点": "七宝万科广场", "具体时间范围": "2024-08-17 10:00:00", "最低票价": "58.0", "Link": "https://show.bilibili.com/platform/detail.html?id=86355", "Cover": "//i1.hdslb.com/bfs/openplatform/202405/UCMNMGbH1716782429997.jpeg"}, {"开始时间": "2024-08-17 - 2024-08-18", "名称": "上海·第六届燃梦BACG PRO动漫嘉年华-我们在燃梦相遇吧！", "地点": "万达汽车乐园(青浦万达茂店)", "具体时间范围": "2024-08-17 11:00:00", "最低票价": "65.8", "Link": "https://show.bilibili.com/platform/detail.html?id=85239", "Cover": "//i1.hdslb.com/bfs/openplatform/202405/mzD4rhY21715109458100.jpeg"}, {"开始时间": "2024-09-15 - 2024-09-16", "名称": "上海·第七届燃梦BACG PRO动漫嘉年华·我们在燃梦相遇吧！", "地点": "七宝万科广场", "具体时间范围": "2024-09-15 10:00:00", "最低票价": "58.0", "Link": "https://show.bilibili.com/platform/detail.html?id=85240", "Cover": "//i2.hdslb.com/bfs/openplatform/202405/RhRh4LZM1715110314459.jpeg"}], "演出": [{"开始时间": "2024-04-05 - 2024-07-13", "名称": "上海·青春无限乐团久石让&宫崎骏&经典影视作品曲目演奏会", "地点": "八号桥艺术空间", "具体时间范围": "2024-04-05 15:50:00", "最低票价": "198.0", "Link": "https://show.bilibili.com/platform/detail.html?id=83612", "Cover": "//i1.hdslb.com/bfs/openplatform/202404/ymKAMdkw1712482600963.jpeg"}, {"开始时间": "2024-05-04 - 2024-07-28", "名称": "上海·动漫主题“双钢琴烛光音乐会”“灌篮高手”海贼王”“天空之城”曲目四手联弹演奏", "地点": "八号桥艺术空间", "具体时间范围": "2024-05-04 14:20:00", "最低票价": "198.0", "Link": "https://show.bilibili.com/platform/detail.html?id=83979", "Cover": "//i0.hdslb.com/bfs/openplatform/202404/XjbxZTRt1712654029166.jpeg"}, {"开始时间": "2024-05-15 - 2024-06-16", "名称": "上海·沉浸式悬念剧场《9号秘事》", "地点": "上海大剧院", "具体时间范围": "2024-05-15 19:30:00", "最低票价": "不可售", "Link": "https://show.bilibili.com/platform/detail.html?id=85208", "Cover": "//i0.hdslb.com/bfs/openplatform/202312/hY6FVnjM1702954652593.jpeg"}, {"开始时间": "2024-06-01 - 2024-06-30", "名称": "上海·喜剧怒谈之《好运日记》", "地点": "WE剧场", "具体时间范围": "2024-06-01 15:00:00", "最低票价": "180.0", "Link": "https://show.bilibili.com/platform/detail.html?id=86480", "Cover": "//i1.hdslb.com/bfs/openplatform/202405/7hy1eP4K1716883508439.jpeg"}, {"开始时间": "2024-06-19", "名称": "上海·奥斯卡·罗曼耶卓钢琴独奏音乐会", "地点": "上海东方艺术中心音乐厅", "具体时间范围": "2024-06-19 19:30:00", "最低票价": "不可售", "Link": "https://show.bilibili.com/platform/detail.html?id=84133", "Cover": "//i2.hdslb.com/bfs/openplatform/202404/7dJtRJNF1712727096117.jpeg"}, {"开始时间": "2024-06-21", "名称": "上海·时光代理人「惊喜节拍」LIVE｜2024音乐巡演", "地点": "Modernsky Lab", "具体时间范围": "2024-06-21 20:00:00", "最低票价": "319.0", "Link": "https://show.bilibili.com/platform/detail.html?id=84957", "Cover": "//i1.hdslb.com/bfs/openplatform/202404/ZdZRs2kZ1714445312787.jpeg"}, {"开始时间": "2024-06-22", "名称": " 上海·2024 JO☆STARS Ft. 长谷川大祐巡回演唱会", "地点": "蜚声上海Livehouse", "具体时间范围": "2024-06-22 13:00:00", "最低票价": "480.0", "Link": "https://show.bilibili.com/platform/detail.html?id=85720", "Cover": "//i2.hdslb.com/bfs/openplatform/202405/iIZFnEhk1715825822760.png"}, {"开始时间": "2024-06-22", "名称": "上海·2024日本电音大神Ken Arai中国巡演 ", "地点": "上海MAO LIVEHOUSE", "具体时间范围": "2024-06-22 20:00:00", "最低票价": "280.0", "Link": "https://show.bilibili.com/platform/detail.html?id=87246", "Cover": "//i0.hdslb.com/bfs/openplatform/202406/O3VKXPyf1718178887801.jpeg"}, {"开始时间": "2024-06-22", "名称": "上海·Liyuu巡回演唱会", "地点": "上海静安体育中心", "具体时间范围": "2024-06-22 19:30:00", "最低票价": "598.0", "Link": "https://show.bilibili.com/platform/detail.html?id=86615", "Cover": "//i2.hdslb.com/bfs/openplatform/202406/3JEYDbl41717557931370.png"}, {"开始时间": "2024-06-22", "名称": "上海·「多厨狂喜」白金交响乐团二次元交响音乐会", "地点": "上海东方艺术中心", "具体时间范围": "2024-06-22 19:30:00", "最低票价": "188.0", "Link": "https://show.bilibili.com/platform/detail.html?id=82731", "Cover": "//i0.hdslb.com/bfs/openplatform/202403/K3AlF8sr1710230449280.jpeg"}, {"开始时间": "2024-06-22", "名称": "上海·声优歌手Machico见面会", "地点": "万代南梦宫上海文化中心", "具体时间范围": "2024-06-22 12:30:00", "最低票价": "398.0", "Link": "https://show.bilibili.com/platform/detail.html?id=85826", "Cover": "//i2.hdslb.com/bfs/openplatform/202405/qaB0z5bf1716006811622.png"}, {"开始时间": "2024-06-23", "名称": "上海·游马晃祐粉丝见面会", "地点": "万代南梦宫上海文化中心", "具体时间范围": "2024-06-23 13:00:00", "最低票价": "480.0", "Link": "https://show.bilibili.com/platform/detail.html?id=84330", "Cover": "//i2.hdslb.com/bfs/openplatform/202404/G0vOG4EZ1713257811188.jpeg"}, {"开始时间": "2024-06-23", "名称": "上海·花之礼赞——《奏响吧，和音社！》经典动漫交响音乐会", "地点": "上海东方艺术中心音乐厅", "具体时间范围": "2024-06-23 19:30:00", "最低票价": "80.0", "Link": "https://show.bilibili.com/platform/detail.html?id=86351", "Cover": "//i2.hdslb.com/bfs/openplatform/202405/0yoP5CT41715675485016.jpeg"}, {"开始时间": "2024-06-28", "名称": "上海·【热血动漫】热血二次元ACG神级动漫巡回演唱会", "地点": "上海东方艺术中心音乐厅", "具体时间范围": "2024-06-28 19:30:00", "最低票价": "108.0", "Link": "https://show.bilibili.com/platform/detail.html?id=86691", "Cover": "//i1.hdslb.com/bfs/openplatform/202405/EE07WaGo1717145849091.jpeg"}, {"开始时间": "2024-06-29", "名称": "上海·《沐云华·次元狂想》经典动漫二次元ACG音乐会—琥珀琴师×Mona×云小鱼", "地点": "上海东方艺术中心音乐厅", "具体时间范围": "2024-06-29 19:30:00", "最低票价": "99.0", "Link": "https://show.bilibili.com/platform/detail.html?id=86546", "Cover": "//i1.hdslb.com/bfs/openplatform/202405/obpyJwk21716875708282.png"}, {"开始时间": "2024-06-30", "名称": "上海·《梁祝》传世经典浪漫唯美名曲音乐会", "地点": "上海东方艺术中心音乐厅", "具体时间范围": "2024-06-30 19:30:00", "最低票价": "80.0", "Link": "https://show.bilibili.com/platform/detail.html?id=84894", "Cover": "//i2.hdslb.com/bfs/openplatform/202404/yRW85YpQ1714103582766.jpeg"}, {"开始时间": "2024-07-05", "名称": "上海·《可爱的中国旋律》藤原育郎电影音乐作品演奏会", "地点": "林肯爵士乐上海中心", "具体时间范围": "2024-07-05 19:30:00", "最低票价": "380.0", "Link": "https://show.bilibili.com/platform/detail.html?id=86951", "Cover": "//i1.hdslb.com/bfs/openplatform/202406/9OuHXjO41717657273152.jpeg"}, {"开始时间": "2024-07-05", "名称": "上海·煮儿果实 2024\"果乐园\"巡回演出", "地点": "上海MAO LIVEHOUSE", "具体时间范围": "2024-07-05 20:00:00", "最低票价": "480.0", "Link": "https://show.bilibili.com/platform/detail.html?id=85937", "Cover": "//i0.hdslb.com/bfs/openplatform/202405/im2VC7nE1716260411672.jpeg"}, {"开始时间": "2024-07-06", "名称": "上海·【早鸟6折】《海上钢琴师1900》一生必听经典电影主题音乐会", "地点": "茉莉花剧场", "具体时间范围": "2024-07-06 19:30:00", "最低票价": "72.0", "Link": "https://show.bilibili.com/platform/detail.html?id=85429", "Cover": "//i1.hdslb.com/bfs/openplatform/202405/ILLS8cRC1715312852863.jpeg"}, {"开始时间": "2024-07-07", "名称": "上海·【国风美学】千古传颂唯美国风音乐会《千年等一回》 ——江苏女子民族乐团", "地点": "上海东方艺术中心音乐厅", "具体时间范围": "2024-07-07 19:30:00", "最低票价": "108.0", "Link": "https://show.bilibili.com/platform/detail.html?id=86693", "Cover": "//i1.hdslb.com/bfs/openplatform/202405/lnLXhUD61717147240259.jpeg"}, {"开始时间": "2024-07-12", "名称": "上海·夜鹿x夜游x真夜中   三夜0nly「夜³歌症候群」联合乐队现场", "地点": "THE BOXX•城市乐园", "具体时间范围": "2024-07-12 19:30:00", "最低票价": "99.0", "Link": "https://show.bilibili.com/platform/detail.html?id=85005", "Cover": "//i2.hdslb.com/bfs/openplatform/202404/NPObaZdG1714384417870.png"}, {"开始时间": "2024-07-13 - 2024-07-14", "名称": "上海·BILIBILI MACRO LINK 2024", "地点": "国家会展中心虹馆EH", "具体时间范围": "2024-07-13 18:00:00", "最低票价": "不可售", "Link": "https://show.bilibili.com/platform/detail.html?id=85938", "Cover": "//i0.hdslb.com/bfs/openplatform/202406/mVoCsUDm1718087957165.jpeg"}, {"开始时间": "2024-07-14", "名称": "上海·2024三浦凉介粉丝见面会&迷你演唱会in上海", "地点": "万代南梦宫上海文化中心-梦想剧场", "具体时间范围": "2024-07-14 12:00:00", "最低票价": "480.0", "Link": "https://show.bilibili.com/platform/detail.html?id=87152", "Cover": "//i2.hdslb.com/bfs/openplatform/202406/1C1GzAcX1718090922129.png"}, {"开始时间": "2024-07-14", "名称": "上海·【早鸟5折】致敬大师·告别之作《你想活出怎样的人生》·宫崎骏&久石让 经典动漫作品音乐会（取消）", "地点": "上海商城剧院", "具体时间范围": "2024-07-14 14:00:00", "最低票价": "不可售", "Link": "https://show.bilibili.com/platform/detail.html?id=84959", "Cover": "//i1.hdslb.com/bfs/openplatform/202404/XMKh0Jg61714275691089.jpeg"}, {"开始时间": "2024-07-14", "名称": "上海·【早鸟6折】《忱宴·渐渐被你吸引》热血动漫二次元ACG演唱会", "地点": "上海商城剧院", "具体时间范围": "2024-07-14 19:30:00", "最低票价": "60.0", "Link": "https://show.bilibili.com/platform/detail.html?id=84955", "Cover": "//i0.hdslb.com/bfs/openplatform/202404/ezCf5M6b1714282322298.png"}, {"开始时间": "2024-07-17", "名称": "上海·石川绫子小提琴动漫音乐会", "地点": "上海东方艺术中心", "具体时间范围": "2024-07-17 19:30:00", "最低票价": "180.0", "Link": "https://show.bilibili.com/platform/detail.html?id=83967", "Cover": "//i1.hdslb.com/bfs/openplatform/202404/HhY3CS7t1712652128640.jpeg"}, {"开始时间": "2024-07-19", "名称": "上海·《你的名字》《天气之子》《铃芽之旅》——新海诚动漫三部曲钢琴演奏会", "地点": "上海东方艺术中心音乐厅", "具体时间范围": "2024-07-19 19:30:00", "最低票价": "80.0", "Link": "https://show.bilibili.com/platform/detail.html?id=83479", "Cover": "//i1.hdslb.com/bfs/openplatform/202403/GpyueuYA1711508106584.jpeg"}, {"开始时间": "2024-07-19", "名称": "上海·《时光机2008·青春重启计划》演唱会", "地点": "瓦肆VAS SHANGHAI", "具体时间范围": "2024-07-19 20:00:00", "最低票价": "128.0", "Link": "https://show.bilibili.com/platform/detail.html?id=86969", "Cover": "//i0.hdslb.com/bfs/openplatform/202406/ajhKui2x1717588730159.png"}, {"开始时间": "2024-07-19", "名称": "上海·燃动!!高梨康治SUMMER LIVE TOUR IN CHINA 2024", "地点": "万代南梦宫上海文化中心", "具体时间范围": "2024-07-19 19:30:00", "最低票价": "280.0", "Link": "https://show.bilibili.com/platform/detail.html?id=87061", "Cover": "//i0.hdslb.com/bfs/openplatform/202406/H9TGguhL1717747212685.png"}, {"开始时间": "2024-07-20", "名称": "上海·变形金刚交响音乐会40周年特别版", "地点": "捷豹上海交响音乐厅", "具体时间范围": "2024-07-20 19:30:00", "最低票价": "266.0", "Link": "https://show.bilibili.com/platform/detail.html?id=84261", "Cover": "//i1.hdslb.com/bfs/openplatform/202404/eqG3fTcX1713104706952.jpeg"}, {"开始时间": "2024-07-21", "名称": "上海·Star2U跨次元嘉年华 vol.12.5～邦邦 Band Only～ ", "地点": "THE BOXX•城市乐园", "具体时间范围": "2024-07-21 14:00:00", "最低票价": "128.0", "Link": "https://show.bilibili.com/platform/detail.html?id=87110", "Cover": "//i1.hdslb.com/bfs/openplatform/202406/hL4TbuYJ1717762241867.jpeg"}, {"开始时间": "2024-07-21", "名称": "上海·藤川千爱2024演唱会", "地点": "万代南梦宫上海文化中心", "具体时间范围": "2024-07-21 16:00:00", "最低票价": "380.0", "Link": "https://show.bilibili.com/platform/detail.html?id=85360", "Cover": "//i0.hdslb.com/bfs/openplatform/202405/Qhk2XOza1715248510067.jpeg"}, {"开始时间": "2024-07-26", "名称": "上海·梁祝之父：何占豪指挥·《梁祝》65周年大型东方交响音乐会", "地点": "上海东方艺术中心音乐厅", "具体时间范围": "2024-07-26 19:30:00", "最低票价": "144.0", "Link": "https://show.bilibili.com/platform/detail.html?id=85591", "Cover": "//i2.hdslb.com/bfs/openplatform/202405/8bMGNbdd1715238003823.jpeg"}, {"开始时间": "2024-08-03", "名称": "上海·《四月是你的谎言》——“公生”与“薰”的钢琴小提琴唯美经典音乐集", "地点": "上海东方艺术中心音乐厅", "具体时间范围": "2024-08-03 19:30:00", "最低票价": "80.0", "Link": "https://show.bilibili.com/platform/detail.html?id=84827", "Cover": "//i1.hdslb.com/bfs/openplatform/202404/hQBaZcog1714011608672.jpeg"}, {"开始时间": "2024-08-03", "名称": "上海·【大乐】《遇见梵高·星月夜》传世经典作品音乐会", "地点": "FANCL艺术中心", "具体时间范围": "2024-08-03 19:30:00", "最低票价": "40.0", "Link": "https://show.bilibili.com/platform/detail.html?id=85516", "Cover": "//i0.hdslb.com/bfs/openplatform/202405/iNr9uRU31715424434015.jpeg"}, {"开始时间": "2024-08-03", "名称": "上海·【神级现场】《冠位时之门：FUN肆二次元》——中华国乐·动漫ACG仲夏夜燃爆之巅", "地点": "加零剧场", "具体时间范围": "2024-08-03 19:30:00", "最低票价": "79.0", "Link": "https://show.bilibili.com/platform/detail.html?id=86821", "Cover": "//i2.hdslb.com/bfs/openplatform/202406/GT7aknBG1717571657329.jpeg"}, {"开始时间": "2024-08-03", "名称": "上海·【神级现场】《冠位时之门：青春回忆时廊》——中华国乐·二次元动漫ACG夏日清凉音乐会", "地点": "加零剧场", "具体时间范围": "2024-08-03 15:15:00", "最低票价": "128.0", "Link": "https://show.bilibili.com/platform/detail.html?id=86842", "Cover": "//i2.hdslb.com/bfs/openplatform/202406/heIkgSe71717657445122.jpeg"}, {"开始时间": "2024-08-16", "名称": "上海·NANO 2024 演唱会  DO OR DIE!! Rock Your Heart Out", "地点": "万代南梦宫上海文化中心", "具体时间范围": "2024-08-16 19:30:00", "最低票价": "380.0", "Link": "https://show.bilibili.com/platform/detail.html?id=87165", "Cover": "//i0.hdslb.com/bfs/openplatform/202406/eVpEGaEI1718094225337.jpeg"}, {"开始时间": "2024-08-17 - 2024-08-25", "名称": "上海·音乐剧《消失的她》", "地点": "北外滩友邦大剧院", "具体时间范围": "2024-08-17 19:30:00", "最低票价": "480.0", "Link": "https://show.bilibili.com/platform/detail.html?id=86983", "Cover": "//i2.hdslb.com/bfs/openplatform/202406/Ks5A4X2i1717652089868.jpeg"}, {"开始时间": "2024-08-18", "名称": "上海·Marcin Patrzalek 2024 《原声之龙》指弹吉他音乐会", "地点": "万代南梦宫上海文化中心", "具体时间范围": "2024-08-18 19:30:00", "最低票价": "不可售", "Link": "https://show.bilibili.com/platform/detail.html?id=86297", "Cover": "//i1.hdslb.com/bfs/openplatform/202405/3y3sBaX31716548345650.jpeg"}, {"开始时间": "2024-08-24", "名称": "上海·幻梦游戏律动——怪物猎人X最终幻想X塞尔达 燃炸游戏室内乐音乐会", "地点": "上海商城剧院", "具体时间范围": "2024-08-24 19:30:00", "最低票价": "88.0", "Link": "https://show.bilibili.com/platform/detail.html?id=85461", "Cover": "//i2.hdslb.com/bfs/openplatform/202405/7fJJ5GxW1715327101441.jpeg"}, {"开始时间": "2024-09-08", "名称": "上海·【哥哥生日场，限量7折】“风继续吹”2024纪念张国荣金曲演唱会", "地点": "上海保利城市剧院", "具体时间范围": "2024-09-08 19:30:00", "最低票价": "128.0", "Link": "https://show.bilibili.com/platform/detail.html?id=87096", "Cover": "//i1.hdslb.com/bfs/openplatform/202406/ROl9e1Ko1717741374852.jpeg"}, {"开始时间": "2024-09-20", "名称": "上海·魔弓传奇III“永恒的梁祝”——吕思清小提琴独奏音乐会", "地点": "北外滩友邦大剧院", "具体时间范围": "2024-09-20 19:30:00", "最低票价": "180.0", "Link": "https://show.bilibili.com/platform/detail.html?id=85044", "Cover": "//i0.hdslb.com/bfs/openplatform/202404/0z6hQm5B1714293642141.jpeg"}], "本地生活": [{"开始时间": "2023-10-16 - 2024-10-15", "名称": "上海·古影文化《1941·新和医院》大型沉浸式互动剧场", "地点": "古影沉浸式互动游戏剧场", "具体时间范围": "2023-10-16 10:00:00", "最低票价": "不可售", "Link": "https://show.bilibili.com/platform/detail.html?id=77530", "Cover": "//i0.hdslb.com/bfs/openplatform/202310/JqP3lHJt1698030195136.jpeg"}, {"开始时间": "2023-10-25 - 2024-10-20", "名称": "上海·方块大战（豫园店）", "地点": "城隍庙第一购物中心", "具体时间范围": "2023-10-25 10:00:00", "最低票价": "不可售", "Link": "https://show.bilibili.com/platform/detail.html?id=79057", "Cover": "//i1.hdslb.com/bfs/openplatform/202312/ASamaqBx1701419480253.jpeg"}, {"开始时间": "2024-05-20 - 2024-06-30", "名称": "上海·战双帕弥什 x HAPPY ZOO主题Cafe", "地点": "虹口德必运动LOFT", "具体时间范围": "2024-05-20 00:00:00", "最低票价": "10.0", "Link": "https://show.bilibili.com/platform/detail.html?id=85642", "Cover": "//i2.hdslb.com/bfs/openplatform/202405/ehdpyJQp1715739281505.png"}, {"开始时间": "2024-05-25 - 2024-07-02", "名称": "上海·「排球少年!!垃圾场决战 × animate cafe」", "地点": "animate cafe上海店", "具体时间范围": "2024-05-25 00:00:00", "最低票价": "30.0", "Link": "https://show.bilibili.com/platform/detail.html?id=85283", "Cover": "//i0.hdslb.com/bfs/openplatform/202405/vy2vecK11715162037223.jpeg"}, {"开始时间": "2024-05-25 - 2024-07-22", "名称": "上海·EVANGELION× PrismLand · 新世纪福音战士官方授权主题店", "地点": "第一百货商业中心", "具体时间范围": "2024-05-25 00:00:00", "最低票价": "20.0", "Link": "https://show.bilibili.com/platform/detail.html?id=85030", "Cover": "//i0.hdslb.com/bfs/openplatform/202404/K3kIpfaB1714445776157.jpeg"}, {"开始时间": "2024-05-25 - 2024-08-31", "名称": "上海·日漫咖啡体验", "地点": "Oasis漫画喫茶", "具体时间范围": "2024-05-25 10:00:00", "最低票价": "60.0", "Link": "https://show.bilibili.com/platform/detail.html?id=86322", "Cover": "//i2.hdslb.com/bfs/openplatform/202405/NXQqtMoH1716197562437.jpeg"}, {"开始时间": "2024-05-25 - 2024-08-31", "名称": "上海·迷你四驱车赛场", "地点": "Oasis漫画喫茶", "具体时间范围": "2024-05-25 10:00:00", "最低票价": "48.0", "Link": "https://show.bilibili.com/platform/detail.html?id=86311", "Cover": "//i1.hdslb.com/bfs/openplatform/202405/Y9t4oITS1716202012481.png"}, {"开始时间": "2024-06-01 - 2024-07-15", "名称": "上海·NIJISANJI EN 官方授权主题店", "地点": "静安大悦城", "具体时间范围": "2024-06-01 00:00:00", "最低票价": "30.0", "Link": "https://show.bilibili.com/platform/detail.html?id=86310", "Cover": "//i0.hdslb.com/bfs/openplatform/202405/MhBVkfZ51716778059321.jpeg"}, {"开始时间": "2024-06-07 - 2024-08-04", "名称": "上海·全职高手×HAPPY ZOO 全职高手十周年咖啡厅", "地点": "HAPPY ZOO", "具体时间范围": "2024-06-07 00:00:00", "最低票价": "10.0", "Link": "https://show.bilibili.com/platform/detail.html?id=86871", "Cover": "//i2.hdslb.com/bfs/openplatform/202406/KLJmCEkC1717568198482.png"}, {"开始时间": "2024-06-08 - 2024-07-21", "名称": "上海· 怪兽8号 meets niko and … 集章之旅    ", "地点": "niko and ... (上海四季坊店)", "具体时间范围": "2024-06-08 10:00:00", "最低票价": "48.0", "Link": "https://show.bilibili.com/platform/detail.html?id=85758", "Cover": "//i0.hdslb.com/bfs/openplatform/202405/xw8aUE5u1715846379865.jpeg"}, {"开始时间": "2024-06-12 - 2024-06-30", "名称": "上海 ·「蓝色监狱 x 次元波板糖」主题餐厅", "地点": "静安大悦城", "具体时间范围": "2024-06-12 00:00:00", "最低票价": "30.0", "Link": "https://show.bilibili.com/platform/detail.html?id=87144", "Cover": "//i0.hdslb.com/bfs/openplatform/202406/budG5Uyl1718089258239.png"}, {"开始时间": "2024-06-14 - 2024-07-07", "名称": "上海·「排球少年!!垃圾场决战」主题店", "地点": "静安大悦城", "具体时间范围": "2024-06-14 00:00:00", "最低票价": "10.0", "Link": "https://show.bilibili.com/platform/detail.html?id=86948", "Cover": "//i1.hdslb.com/bfs/openplatform/202406/GxQRrJ2V1717655942245.png"}, {"开始时间": "2024-06-15 - 2024-07-04", "名称": "上海·2024·《心跳嘉年华 碧蓝航线cafe补给站第一期》x  萌果酱谷子咖啡", "地点": "萌果酱谷子咖啡（百联）", "具体时间范围": "2024-06-15 00:00:00", "最低票价": "30.0", "Link": "https://show.bilibili.com/platform/detail.html?id=87003", "Cover": "//i2.hdslb.com/bfs/openplatform/202406/hEVeQbVK1717669735881.png"}, {"开始时间": "2024-07-05 - 2024-07-30", "名称": "上海·「剧场版BLUE LOCK -EPISODE凪- 」", "地点": "animate cafe上海店", "具体时间范围": "2024-07-05 00:00:00", "最低票价": "30.0", "Link": "https://show.bilibili.com/platform/detail.html?id=87171", "Cover": "//i1.hdslb.com/bfs/openplatform/202406/9TBGVLTf1718097565516.png"}], "全部类型": [{"开始时间": "2023-10-16 - 2024-10-15", "名称": "上海·古影文化《1941·新和医院》大型沉浸式互动剧场", "地点": "古影沉浸式互动游戏剧场", "具体时间范围": "2023-10-16 10:00:00", "最低票价": "不可售", "Link": "https://show.bilibili.com/platform/detail.html?id=77530", "Cover": "//i0.hdslb.com/bfs/openplatform/202310/JqP3lHJt1698030195136.jpeg"}, {"开始时间": "2023-10-25 - 2024-10-20", "名称": "上海·方块大战（豫园店）", "地点": "城隍庙第一购物中心", "具体时间范围": "2023-10-25 10:00:00", "最低票价": "不可售", "Link": "https://show.bilibili.com/platform/detail.html?id=79057", "Cover": "//i1.hdslb.com/bfs/openplatform/202312/ASamaqBx1701419480253.jpeg"}, {"开始时间": "2024-04-05 - 2024-07-13", "名称": "上海·青春无限乐团久石让&宫崎骏&经典影视作品曲目演奏会", "地点": "八号桥艺术空间", "具体时间范围": "2024-04-05 15:50:00", "最低票价": "198.0", "Link": "https://show.bilibili.com/platform/detail.html?id=83612", "Cover": "//i1.hdslb.com/bfs/openplatform/202404/ymKAMdkw1712482600963.jpeg"}, {"开始时间": "2024-04-12 - 2024-06-30", "名称": "上海·吉卜力工作室物语-沉浸式艺术展全球首站", "地点": "上海国际传媒港艺术中心", "具体时间范围": "2024-04-12 10:00:00", "最低票价": "88.0", "Link": "https://show.bilibili.com/platform/detail.html?id=83036", "Cover": "//i0.hdslb.com/bfs/openplatform/202403/aZoum5Hd1710472525792.jpeg"}, {"开始时间": "2024-05-04 - 2024-07-28", "名称": "上海·动漫主题“双钢琴烛光音乐会”“灌篮高手”海贼王”“天空之城”曲目四手联弹演奏", "地点": "八号桥艺术空间", "具体时间范围": "2024-05-04 14:20:00", "最低票价": "198.0", "Link": "https://show.bilibili.com/platform/detail.html?id=83979", "Cover": "//i0.hdslb.com/bfs/openplatform/202404/XjbxZTRt1712654029166.jpeg"}, {"开始时间": "2024-05-15 - 2024-06-16", "名称": "上海·沉浸式悬念剧场《9号秘事》", "地点": "上海大剧院", "具体时间范围": "2024-05-15 19:30:00", "最低票价": "不可售", "Link": "https://show.bilibili.com/platform/detail.html?id=85208", "Cover": "//i0.hdslb.com/bfs/openplatform/202312/hY6FVnjM1702954652593.jpeg"}, {"开始时间": "2024-05-20 - 2024-06-30", "名称": "上海·战双帕弥什 x HAPPY ZOO主题Cafe", "地点": "虹口德必运动LOFT", "具体时间范围": "2024-05-20 00:00:00", "最低票价": "10.0", "Link": "https://show.bilibili.com/platform/detail.html?id=85642", "Cover": "//i2.hdslb.com/bfs/openplatform/202405/ehdpyJQp1715739281505.png"}, {"开始时间": "2024-05-25 - 2024-07-02", "名称": "上海·「排球少年!!垃圾场决战 × animate cafe」", "地点": "animate cafe上海店", "具体时间范围": "2024-05-25 00:00:00", "最低票价": "30.0", "Link": "https://show.bilibili.com/platform/detail.html?id=85283", "Cover": "//i0.hdslb.com/bfs/openplatform/202405/vy2vecK11715162037223.jpeg"}, {"开始时间": "2024-05-25 - 2024-07-22", "名称": "上海·EVANGELION× PrismLand · 新世纪福音战士官方授权主题店", "地点": "第一百货商业中心", "具体时间范围": "2024-05-25 00:00:00", "最低票价": "20.0", "Link": "https://show.bilibili.com/platform/detail.html?id=85030", "Cover": "//i0.hdslb.com/bfs/openplatform/202404/K3kIpfaB1714445776157.jpeg"}, {"开始时间": "2024-05-25 - 2024-08-18", "名称": "上海·《宫西达也的绘本世界》", "地点": "合生汇", "具体时间范围": "2024-05-25 10:00:00", "最低票价": "88.0", "Link": "https://show.bilibili.com/platform/detail.html?id=86496", "Cover": "//i1.hdslb.com/bfs/openplatform/202405/aSUGj8i31716949002492.jpeg"}, {"开始时间": "2024-05-25 - 2024-08-31", "名称": "上海·日漫咖啡体验", "地点": "Oasis漫画喫茶", "具体时间范围": "2024-05-25 10:00:00", "最低票价": "60.0", "Link": "https://show.bilibili.com/platform/detail.html?id=86322", "Cover": "//i2.hdslb.com/bfs/openplatform/202405/NXQqtMoH1716197562437.jpeg"}, {"开始时间": "2024-05-25 - 2024-08-31", "名称": "上海·迷你四驱车赛场", "地点": "Oasis漫画喫茶", "具体时间范围": "2024-05-25 10:00:00", "最低票价": "48.0", "Link": "https://show.bilibili.com/platform/detail.html?id=86311", "Cover": "//i1.hdslb.com/bfs/openplatform/202405/Y9t4oITS1716202012481.png"}, {"开始时间": "2024-06-01 - 2024-06-30", "名称": "上海·喜剧怒谈之《好运日记》", "地点": "WE剧场", "具体时间范围": "2024-06-01 15:00:00", "最低票价": "180.0", "Link": "https://show.bilibili.com/platform/detail.html?id=86480", "Cover": "//i1.hdslb.com/bfs/openplatform/202405/7hy1eP4K1716883508439.jpeg"}, {"开始时间": "2024-06-01 - 2024-06-30", "名称": "上海·秦潮觉醒沉浸式探索体验", "地点": "秦潮觉醒XR沉浸体验展", "具体时间范围": "2024-06-01 10:00:00", "最低票价": "不可售", "Link": "https://show.bilibili.com/platform/detail.html?id=85604", "Cover": "//i1.hdslb.com/bfs/openplatform/202405/Ll4BZQLw1715658305492.png"}, {"开始时间": "2024-06-01 - 2024-07-15", "名称": "上海·NIJISANJI EN 官方授权主题店", "地点": "静安大悦城", "具体时间范围": "2024-06-01 00:00:00", "最低票价": "30.0", "Link": "https://show.bilibili.com/platform/detail.html?id=86310", "Cover": "//i0.hdslb.com/bfs/openplatform/202405/MhBVkfZ51716778059321.jpeg"}, {"开始时间": "2024-06-07 - 2024-08-04", "名称": "上海·全职高手×HAPPY ZOO 全职高手十周年咖啡厅", "地点": "HAPPY ZOO", "具体时间范围": "2024-06-07 00:00:00", "最低票价": "10.0", "Link": "https://show.bilibili.com/platform/detail.html?id=86871", "Cover": "//i2.hdslb.com/bfs/openplatform/202406/KLJmCEkC1717568198482.png"}, {"开始时间": "2024-06-08 - 2024-07-21", "名称": "上海· 怪兽8号 meets niko and … 集章之旅    ", "地点": "niko and ... (上海四季坊店)", "具体时间范围": "2024-06-08 10:00:00", "最低票价": "48.0", "Link": "https://show.bilibili.com/platform/detail.html?id=85758", "Cover": "//i0.hdslb.com/bfs/openplatform/202405/xw8aUE5u1715846379865.jpeg"}, {"开始时间": "2024-06-08 - 2024-10-07", "名称": "上海·无穹-中国 航天沉浸艺术展", "地点": "上海喜玛拉雅美术馆", "具体时间范围": "2024-06-08 10:00:00", "最低票价": "78.0", "Link": "https://show.bilibili.com/platform/detail.html?id=86957", "Cover": "//i1.hdslb.com/bfs/openplatform/202406/Bus3lAnI1717558639134.jpeg"}, {"开始时间": "2024-06-12 - 2024-06-30", "名称": "上海 ·「蓝色监狱 x 次元波板糖」主题餐厅", "地点": "静安大悦城", "具体时间范围": "2024-06-12 00:00:00", "最低票价": "30.0", "Link": "https://show.bilibili.com/platform/detail.html?id=87144", "Cover": "//i0.hdslb.com/bfs/openplatform/202406/budG5Uyl1718089258239.png"}, {"开始时间": "2024-06-14 - 2024-07-07", "名称": "上海·「排球少年!!垃圾场决战」主题店", "地点": "静安大悦城", "具体时间范围": "2024-06-14 00:00:00", "最低票价": "10.0", "Link": "https://show.bilibili.com/platform/detail.html?id=86948", "Cover": "//i1.hdslb.com/bfs/openplatform/202406/GxQRrJ2V1717655942245.png"}, {"开始时间": "2024-06-15 - 2024-06-16", "名称": "上海·第二届环绕银河动漫游戏嘉年华·音你跃动", "地点": "PK西餐厅运动娱乐中心(普陀信泰中心店)", "具体时间范围": "2024-06-15 10:00:00", "最低票价": "78.0", "Link": "https://show.bilibili.com/platform/detail.html?id=86513", "Cover": "//i0.hdslb.com/bfs/openplatform/202405/Gk5tu5E41716866802069.jpeg"}, {"开始时间": "2024-06-15 - 2024-07-04", "名称": "上海·2024·《心跳嘉年华 碧蓝航线cafe补给站第一期》x  萌果酱谷子咖啡", "地点": "萌果酱谷子咖啡（百联）", "具体时间范围": "2024-06-15 00:00:00", "最低票价": "30.0", "Link": "https://show.bilibili.com/platform/detail.html?id=87003", "Cover": "//i2.hdslb.com/bfs/openplatform/202406/hEVeQbVK1717669735881.png"}, {"开始时间": "2024-06-16", "名称": "上海·宅舞联萌·随舞动漫派对（免费活动）", "地点": "百脑汇(漕溪北路旗舰店)", "具体时间范围": "2024-06-16 14:00:00", "最低票价": "22.33", "Link": "https://show.bilibili.com/platform/detail.html?id=85656", "Cover": "//i2.hdslb.com/bfs/openplatform/202405/NV0dnyhg1715755075562.jpeg"}, {"开始时间": "2024-06-19", "名称": "上海·奥斯卡·罗曼耶卓钢琴独奏音乐会", "地点": "上海东方艺术中心音乐厅", "具体时间范围": "2024-06-19 19:30:00", "最低票价": "不可售", "Link": "https://show.bilibili.com/platform/detail.html?id=84133", "Cover": "//i2.hdslb.com/bfs/openplatform/202404/7dJtRJNF1712727096117.jpeg"}, {"开始时间": "2024-06-21", "名称": "上海·时光代理人「惊喜节拍」LIVE｜2024音乐巡演", "地点": "Modernsky Lab", "具体时间范围": "2024-06-21 20:00:00", "最低票价": "319.0", "Link": "https://show.bilibili.com/platform/detail.html?id=84957", "Cover": "//i1.hdslb.com/bfs/openplatform/202404/ZdZRs2kZ1714445312787.jpeg"}, {"开始时间": "2024-06-21 - 2024-06-23", "名称": "上海·第一届触圈动漫(CQ)展", "地点": "静安国际科创社区云芯科创中心", "具体时间范围": "2024-06-21 14:00:00", "最低票价": "70.0", "Link": "https://show.bilibili.com/platform/detail.html?id=85312", "Cover": "//i0.hdslb.com/bfs/openplatform/202405/QPXgNO6X1715222404042.png"}, {"开始时间": "2024-06-22", "名称": " 上海·2024 JO☆STARS Ft. 长谷川大祐巡回演唱会", "地点": "蜚声上海Livehouse", "具体时间范围": "2024-06-22 13:00:00", "最低票价": "480.0", "Link": "https://show.bilibili.com/platform/detail.html?id=85720", "Cover": "//i2.hdslb.com/bfs/openplatform/202405/iIZFnEhk1715825822760.png"}, {"开始时间": "2024-06-22", "名称": "上海 星芒旋转 二次元团建狂欢日", "地点": "JUMP工坊", "具体时间范围": "2024-06-22 14:00:00", "最低票价": "60.0", "Link": "https://show.bilibili.com/platform/detail.html?id=86361", "Cover": "//i0.hdslb.com/bfs/openplatform/202405/NjWMqWjm1716797273634.jpeg"}, {"开始时间": "2024-06-22", "名称": "上海·2024日本电音大神Ken Arai中国巡演 ", "地点": "上海MAO LIVEHOUSE", "具体时间范围": "2024-06-22 20:00:00", "最低票价": "280.0", "Link": "https://show.bilibili.com/platform/detail.html?id=87246", "Cover": "//i0.hdslb.com/bfs/openplatform/202406/O3VKXPyf1718178887801.jpeg"}, {"开始时间": "2024-06-22", "名称": "上海·622cp金婚only·沉沦", "地点": "丽丽薇里婚嫁礼堂婚宴(闵行店)", "具体时间范围": "2024-06-22 11:00:00", "最低票价": "68.0", "Link": "https://show.bilibili.com/platform/detail.html?id=85430", "Cover": "//i1.hdslb.com/bfs/openplatform/202405/vlXVjLBA1715077227390.png"}, {"开始时间": "2024-06-22", "名称": "上海·Liyuu巡回演唱会", "地点": "上海静安体育中心", "具体时间范围": "2024-06-22 19:30:00", "最低票价": "598.0", "Link": "https://show.bilibili.com/platform/detail.html?id=86615", "Cover": "//i2.hdslb.com/bfs/openplatform/202406/3JEYDbl41717557931370.png"}, {"开始时间": "2024-06-22", "名称": "上海·「多厨狂喜」白金交响乐团二次元交响音乐会", "地点": "上海东方艺术中心", "具体时间范围": "2024-06-22 19:30:00", "最低票价": "188.0", "Link": "https://show.bilibili.com/platform/detail.html?id=82731", "Cover": "//i0.hdslb.com/bfs/openplatform/202403/K3AlF8sr1710230449280.jpeg"}, {"开始时间": "2024-06-22", "名称": "上海·声优歌手Machico见面会", "地点": "万代南梦宫上海文化中心", "具体时间范围": "2024-06-22 12:30:00", "最低票价": "398.0", "Link": "https://show.bilibili.com/platform/detail.html?id=85826", "Cover": "//i2.hdslb.com/bfs/openplatform/202405/qaB0z5bf1716006811622.png"}, {"开始时间": "2024-06-22", "名称": "上海·第五人格only", "地点": "竞梦元宇宙", "具体时间范围": "2024-06-22 10:00:00", "最低票价": "68.0", "Link": "https://show.bilibili.com/platform/detail.html?id=86971", "Cover": "//i1.hdslb.com/bfs/openplatform/202406/OOItNE0E1717592352095.png"}, {"开始时间": "2024-06-22 - 2024-06-23", "名称": "上海·COMICBLISS动漫嘉年华", "地点": "上海大世界", "具体时间范围": "2024-06-22 09:30:00", "最低票价": "68.0", "Link": "https://show.bilibili.com/platform/detail.html?id=86901", "Cover": "//i1.hdslb.com/bfs/openplatform/202406/KQjSSavY1717558632149.jpeg"}, {"开始时间": "2024-06-22 - 2024-06-23", "名称": "上海·第八届Redamancy动漫游戏嘉年华", "地点": "环球港上海世嘉都市乐园", "具体时间范围": "2024-06-22 10:00:00", "最低票价": "60.0", "Link": "https://show.bilibili.com/platform/detail.html?id=84635", "Cover": "//i2.hdslb.com/bfs/openplatform/202404/EadsJBh41713193501329.png"}, {"开始时间": "2024-06-22 - 2024-06-23", "名称": "上海·第六十二届燃梦星辰动漫嘉年华", "地点": "尚优里·乐坊生活广场", "具体时间范围": "2024-06-22 10:00:00", "最低票价": "58.8", "Link": "https://show.bilibili.com/platform/detail.html?id=85751", "Cover": "//i0.hdslb.com/bfs/openplatform/202405/lMjgV8wr1715842872181.jpeg"}, {"开始时间": "2024-06-22 - 2024-06-23", "名称": "上海·运动番only", "地点": "中成智谷", "具体时间范围": "2024-06-22 10:00:00", "最低票价": "89.0", "Link": "https://show.bilibili.com/platform/detail.html?id=87122", "Cover": "//i0.hdslb.com/bfs/openplatform/202406/Dhx52mWP1717689592171.jpeg"}, {"开始时间": "2024-06-23", "名称": "上海·原神×星穹铁道ONLY", "地点": "竞梦元宇宙", "具体时间范围": "2024-06-23 10:00:00", "最低票价": "68.0", "Link": "https://show.bilibili.com/platform/detail.html?id=87157", "Cover": "//i2.hdslb.com/bfs/openplatform/202406/imNmTcWA1718078981607.png"}, {"开始时间": "2024-06-23", "名称": "上海·游马晃祐粉丝见面会", "地点": "万代南梦宫上海文化中心", "具体时间范围": "2024-06-23 13:00:00", "最低票价": "480.0", "Link": "https://show.bilibili.com/platform/detail.html?id=84330", "Cover": "//i2.hdslb.com/bfs/openplatform/202404/G0vOG4EZ1713257811188.jpeg"}, {"开始时间": "2024-06-23", "名称": "上海·花之礼赞——《奏响吧，和音社！》经典动漫交响音乐会", "地点": "上海东方艺术中心音乐厅", "具体时间范围": "2024-06-23 19:30:00", "最低票价": "80.0", "Link": "https://show.bilibili.com/platform/detail.html?id=86351", "Cover": "//i2.hdslb.com/bfs/openplatform/202405/0yoP5CT41715675485016.jpeg"}, {"开始时间": "2024-06-28", "名称": "上海·【热血动漫】热血二次元ACG神级动漫巡回演唱会", "地点": "上海东方艺术中心音乐厅", "具体时间范围": "2024-06-28 19:30:00", "最低票价": "108.0", "Link": "https://show.bilibili.com/platform/detail.html?id=86691", "Cover": "//i1.hdslb.com/bfs/openplatform/202405/EE07WaGo1717145849091.jpeg"}, {"开始时间": "2024-06-29", "名称": "上海·《沐云华·次元狂想》经典动漫二次元ACG音乐会—琥珀琴师×Mona×云小鱼", "地点": "上海东方艺术中心音乐厅", "具体时间范围": "2024-06-29 19:30:00", "最低票价": "99.0", "Link": "https://show.bilibili.com/platform/detail.html?id=86546", "Cover": "//i1.hdslb.com/bfs/openplatform/202405/obpyJwk21716875708282.png"}, {"开始时间": "2024-06-29", "名称": "上海·咒术回战only（取消）", "地点": "云海大厦", "具体时间范围": "2024-06-29 10:00:00", "最低票价": "不可售", "Link": "https://show.bilibili.com/platform/detail.html?id=85055", "Cover": "//i0.hdslb.com/bfs/openplatform/202404/QeHd0lP91714108380981.png"}, {"开始时间": "2024-06-29", "名称": "上海·第六十三届燃梦星辰动漫嘉年华", "地点": "佘山·旭辉里", "具体时间范围": "2024-06-29 14:00:00", "最低票价": "58.8", "Link": "https://show.bilibili.com/platform/detail.html?id=85231", "Cover": "//i2.hdslb.com/bfs/openplatform/202406/Tx1g80PC1717667546414.jpeg"}, {"开始时间": "2024-06-29", "名称": "上海·葬送的芙莉莲ONLY", "地点": "上海宝丰联大酒店", "具体时间范围": "2024-06-29 10:00:00", "最低票价": "65.0", "Link": "https://show.bilibili.com/platform/detail.html?id=85193", "Cover": "//i2.hdslb.com/bfs/openplatform/202404/VIM2lfxY1714361685906.jpeg"}, {"开始时间": "2024-06-29 - 2024-06-30", "名称": "上海·cdc动漫展", "地点": "JUMP工坊", "具体时间范围": "2024-06-29 10:00:00", "最低票价": "60.0", "Link": "https://show.bilibili.com/platform/detail.html?id=85110", "Cover": "//i2.hdslb.com/bfs/openplatform/202405/RMpaP6sF1714725969882.jpeg"}, {"开始时间": "2024-06-29 - 2024-06-30", "名称": "上海·创世次元动漫游戏嘉年华3.0", "地点": "轮客行轮滑馆(普陀店)", "具体时间范围": "2024-06-29 10:00:00", "最低票价": "58.0", "Link": "https://show.bilibili.com/platform/detail.html?id=86506", "Cover": "//i2.hdslb.com/bfs/openplatform/202405/Clkfdwic1716894666596.jpeg"}, {"开始时间": "2024-06-29 - 2024-06-30", "名称": "上海·第十届Redamancy动漫游戏嘉年华", "地点": "上海JOYPOLIS世嘉都市乐园", "具体时间范围": "2024-06-29 10:00:00", "最低票价": "60.0", "Link": "https://show.bilibili.com/platform/detail.html?id=87334", "Cover": "//i0.hdslb.com/bfs/openplatform/202406/CJQAn6r81718289624171.png"}, {"开始时间": "2024-06-30", "名称": "上海 星芒旋转 anikura动漫嘉年华", "地点": "JUMP工坊", "具体时间范围": "2024-06-30 17:00:00", "最低票价": "60.0", "Link": "https://show.bilibili.com/platform/detail.html?id=86357", "Cover": "//i2.hdslb.com/bfs/openplatform/202405/RAjlTt6f1716788945862.jpeg"}, {"开始时间": "2024-06-30", "名称": "上海·《梁祝》传世经典浪漫唯美名曲音乐会", "地点": "上海东方艺术中心音乐厅", "具体时间范围": "2024-06-30 19:30:00", "最低票价": "80.0", "Link": "https://show.bilibili.com/platform/detail.html?id=84894", "Cover": "//i2.hdslb.com/bfs/openplatform/202404/yRW85YpQ1714103582766.jpeg"}, {"开始时间": "2024-07-05", "名称": "上海·《可爱的中国旋律》藤原育郎电影音乐作品演奏会", "地点": "林肯爵士乐上海中心", "具体时间范围": "2024-07-05 19:30:00", "最低票价": "380.0", "Link": "https://show.bilibili.com/platform/detail.html?id=86951", "Cover": "//i1.hdslb.com/bfs/openplatform/202406/9OuHXjO41717657273152.jpeg"}, {"开始时间": "2024-07-05", "名称": "上海·煮儿果实 2024\"果乐园\"巡回演出", "地点": "上海MAO LIVEHOUSE", "具体时间范围": "2024-07-05 20:00:00", "最低票价": "480.0", "Link": "https://show.bilibili.com/platform/detail.html?id=85937", "Cover": "//i0.hdslb.com/bfs/openplatform/202405/im2VC7nE1716260411672.jpeg"}, {"开始时间": "2024-07-05 - 2024-07-06", "名称": "上海·第三届GSCG动漫节", "地点": "上海大世界", "具体时间范围": "2024-07-05 10:00:00", "最低票价": "75.0", "Link": "https://show.bilibili.com/platform/detail.html?id=86561", "Cover": "//i1.hdslb.com/bfs/openplatform/202405/p5iDI2Mp1717031467789.png"}, {"开始时间": "2024-07-05 - 2024-07-07", "名称": "上海·NW新界动漫游戏展2.0", "地点": "月星家居", "具体时间范围": "2024-07-05 10:00:00", "最低票价": "59.0", "Link": "https://show.bilibili.com/platform/detail.html?id=83923", "Cover": "//i1.hdslb.com/bfs/openplatform/202404/nUixyAy21712605861917.jpeg"}, {"开始时间": "2024-07-05 - 2024-07-30", "名称": "上海·「剧场版BLUE LOCK -EPISODE凪- 」", "地点": "animate cafe上海店", "具体时间范围": "2024-07-05 00:00:00", "最低票价": "30.0", "Link": "https://show.bilibili.com/platform/detail.html?id=87171", "Cover": "//i1.hdslb.com/bfs/openplatform/202406/9TBGVLTf1718097565516.png"}, {"开始时间": "2024-07-06", "名称": "上海·【早鸟6折】《海上钢琴师1900》一生必听经典电影主题音乐会", "地点": "茉莉花剧场", "具体时间范围": "2024-07-06 19:30:00", "最低票价": "72.0", "Link": "https://show.bilibili.com/platform/detail.html?id=85429", "Cover": "//i1.hdslb.com/bfs/openplatform/202405/ILLS8cRC1715312852863.jpeg"}, {"开始时间": "2024-07-06", "名称": "上海·全职猎人ONLY2.0 · 友客鑫拍卖会", "地点": "交运智慧湾科创园25号楼", "具体时间范围": "2024-07-06 10:00:00", "最低票价": "89.0", "Link": "https://show.bilibili.com/platform/detail.html?id=87214", "Cover": "//i0.hdslb.com/bfs/openplatform/202406/Nq3CyukM1718174450980.jpeg"}, {"开始时间": "2024-07-06", "名称": "上海·创世次元动漫游戏嘉年华4.0", "地点": "轮客行轮滑馆(普陀店)", "具体时间范围": "2024-07-06 10:00:00", "最低票价": "58.0", "Link": "https://show.bilibili.com/platform/detail.html?id=86339", "Cover": "//i0.hdslb.com/bfs/openplatform/202406/4xvoJEpz1718353272334.jpeg"}, {"开始时间": "2024-07-06", "名称": "上海·第五人格ONLY3.0", "地点": "诺宝中心酒店", "具体时间范围": "2024-07-06 10:00:00", "最低票价": "60.0", "Link": "https://show.bilibili.com/platform/detail.html?id=86058", "Cover": "//i2.hdslb.com/bfs/openplatform/202405/b9vpuu711716280652600.jpeg"}, {"开始时间": "2024-07-06 - 2024-07-07", "名称": "上海·坏孩纸物语の第45届动漫节之俞伯牙篇", "地点": "徐汇日月光中心", "具体时间范围": "2024-07-06 13:00:00", "最低票价": "55.6", "Link": "https://show.bilibili.com/platform/detail.html?id=86330", "Cover": "//i0.hdslb.com/bfs/openplatform/202405/us2hihO11716292063340.png"}, {"开始时间": "2024-07-06 - 2024-07-08", "名称": "上海·2024圣杯战争（取消）", "地点": "星零界", "具体时间范围": "2024-07-06 11:00:00", "最低票价": "不可售", "Link": "https://show.bilibili.com/platform/detail.html?id=85209", "Cover": "//i2.hdslb.com/bfs/openplatform/202405/P8ulUjVk1715743291864.jpeg"}, {"开始时间": "2024-07-07", "名称": "上海·【国风美学】千古传颂唯美国风音乐会《千年等一回》 ——江苏女子民族乐团", "地点": "上海东方艺术中心音乐厅", "具体时间范围": "2024-07-07 19:30:00", "最低票价": "108.0", "Link": "https://show.bilibili.com/platform/detail.html?id=86693", "Cover": "//i1.hdslb.com/bfs/openplatform/202405/lnLXhUD61717147240259.jpeg"}, {"开始时间": "2024-07-12", "名称": "上海·夜鹿x夜游x真夜中   三夜0nly「夜³歌症候群」联合乐队现场", "地点": "THE BOXX•城市乐园", "具体时间范围": "2024-07-12 19:30:00", "最低票价": "99.0", "Link": "https://show.bilibili.com/platform/detail.html?id=85005", "Cover": "//i2.hdslb.com/bfs/openplatform/202404/NPObaZdG1714384417870.png"}, {"开始时间": "2024-07-12 - 2024-07-14", "名称": "上海·BilibiliWorld 2024", "地点": "上海国家会展中心", "具体时间范围": "2024-07-12 08:30:00", "最低票价": "不可售", "Link": "https://show.bilibili.com/platform/detail.html?id=85939", "Cover": "//i2.hdslb.com/bfs/openplatform/202406/k0Telb2o1717492841341.jpeg"}, {"开始时间": "2024-07-12 - 2024-07-14", "名称": "上海·魔都COS Voice暑假漫展", "地点": "月星家居", "具体时间范围": "2024-07-12 10:00:00", "最低票价": "49.0", "Link": "https://show.bilibili.com/platform/detail.html?id=84008", "Cover": "//i2.hdslb.com/bfs/openplatform/202404/jldYwFXi1712678080397.jpeg"}, {"开始时间": "2024-07-13", "名称": "上海·太中only", "地点": "诺宝中心酒店", "具体时间范围": "2024-07-13 10:00:00", "最低票价": "已售罄", "Link": "https://show.bilibili.com/platform/detail.html?id=84763", "Cover": "//i0.hdslb.com/bfs/openplatform/202404/SHjjt67q1713842062371.jpeg"}, {"开始时间": "2024-07-13", "名称": "上海·恋与深空only【女生专场】", "地点": "竞梦元宇宙", "具体时间范围": "2024-07-13 11:00:00", "最低票价": "88.0", "Link": "https://show.bilibili.com/platform/detail.html?id=87346", "Cover": "//i2.hdslb.com/bfs/openplatform/202406/vaE8H0CC1718081128645.jpeg"}, {"开始时间": "2024-07-13 - 2024-07-14", "名称": "上海·BILIBILI MACRO LINK 2024", "地点": "国家会展中心虹馆EH", "具体时间范围": "2024-07-13 18:00:00", "最低票价": "不可售", "Link": "https://show.bilibili.com/platform/detail.html?id=85938", "Cover": "//i0.hdslb.com/bfs/openplatform/202406/mVoCsUDm1718087957165.jpeg"}, {"开始时间": "2024-07-13 - 2024-07-14", "名称": "上海·coser动漫展", "地点": "JUMP工坊", "具体时间范围": "2024-07-13 10:00:00", "最低票价": "60.0", "Link": "https://show.bilibili.com/platform/detail.html?id=87347", "Cover": "//i2.hdslb.com/bfs/openplatform/202406/gQC62xhm1718287366020.jpeg"}, {"开始时间": "2024-07-13 - 2024-07-14", "名称": "上海·坏孩纸物语の第47届动漫节之钟子期篇", "地点": "徐汇日月光中心", "具体时间范围": "2024-07-13 13:00:00", "最低票价": "56.9", "Link": "https://show.bilibili.com/platform/detail.html?id=86328", "Cover": "//i1.hdslb.com/bfs/openplatform/202405/7OYHZx0z1716292227567.png"}, {"开始时间": "2024-07-13 - 2024-07-14", "名称": "上海·第五届燃梦BACG PRO动漫嘉年华·我们在燃梦相遇吧！", "地点": "万达汽车乐园(青浦万达茂店)", "具体时间范围": "2024-07-13 11:00:00", "最低票价": "65.8", "Link": "https://show.bilibili.com/platform/detail.html?id=85235", "Cover": "//i2.hdslb.com/bfs/openplatform/202405/A9VkjJzh1715108077210.jpeg"}, {"开始时间": "2024-07-13 - 2024-07-14", "名称": "上海·第十三届ACBC动漫盛典（免费活动）", "地点": "LALA STATION上海莲花路店", "具体时间范围": "2024-07-13 10:00:00", "最低票价": "80.0", "Link": "https://show.bilibili.com/platform/detail.html?id=87158", "Cover": "//i1.hdslb.com/bfs/openplatform/202406/sYfCPdla1718084897256.jpeg"}, {"开始时间": "2024-07-14", "名称": "上海·2024三浦凉介粉丝见面会&迷你演唱会in上海", "地点": "万代南梦宫上海文化中心-梦想剧场", "具体时间范围": "2024-07-14 12:00:00", "最低票价": "480.0", "Link": "https://show.bilibili.com/platform/detail.html?id=87152", "Cover": "//i2.hdslb.com/bfs/openplatform/202406/1C1GzAcX1718090922129.png"}, {"开始时间": "2024-07-14", "名称": "上海·【早鸟5折】致敬大师·告别之作《你想活出怎样的人生》·宫崎骏&久石让 经典动漫作品音乐会（取消）", "地点": "上海商城剧院", "具体时间范围": "2024-07-14 14:00:00", "最低票价": "不可售", "Link": "https://show.bilibili.com/platform/detail.html?id=84959", "Cover": "//i1.hdslb.com/bfs/openplatform/202404/XMKh0Jg61714275691089.jpeg"}, {"开始时间": "2024-07-14", "名称": "上海·【早鸟6折】《忱宴·渐渐被你吸引》热血动漫二次元ACG演唱会", "地点": "上海商城剧院", "具体时间范围": "2024-07-14 19:30:00", "最低票价": "60.0", "Link": "https://show.bilibili.com/platform/detail.html?id=84955", "Cover": "//i0.hdslb.com/bfs/openplatform/202404/ezCf5M6b1714282322298.png"}, {"开始时间": "2024-07-14", "名称": "上海·囚鸢代号鸢Only【女生专场】", "地点": "竞梦元宇宙", "具体时间范围": "2024-07-14 11:00:00", "最低票价": "88.0", "Link": "https://show.bilibili.com/platform/detail.html?id=87331", "Cover": "//i1.hdslb.com/bfs/openplatform/202406/e053lkLC1718164512192.jpeg"}, {"开始时间": "2024-07-17", "名称": "上海·石川绫子小提琴动漫音乐会", "地点": "上海东方艺术中心", "具体时间范围": "2024-07-17 19:30:00", "最低票价": "180.0", "Link": "https://show.bilibili.com/platform/detail.html?id=83967", "Cover": "//i1.hdslb.com/bfs/openplatform/202404/HhY3CS7t1712652128640.jpeg"}, {"开始时间": "2024-07-19", "名称": "上海·《你的名字》《天气之子》《铃芽之旅》——新海诚动漫三部曲钢琴演奏会", "地点": "上海东方艺术中心音乐厅", "具体时间范围": "2024-07-19 19:30:00", "最低票价": "80.0", "Link": "https://show.bilibili.com/platform/detail.html?id=83479", "Cover": "//i1.hdslb.com/bfs/openplatform/202403/GpyueuYA1711508106584.jpeg"}, {"开始时间": "2024-07-19", "名称": "上海·《时光机2008·青春重启计划》演唱会", "地点": "瓦肆VAS SHANGHAI", "具体时间范围": "2024-07-19 20:00:00", "最低票价": "128.0", "Link": "https://show.bilibili.com/platform/detail.html?id=86969", "Cover": "//i0.hdslb.com/bfs/openplatform/202406/ajhKui2x1717588730159.png"}, {"开始时间": "2024-07-19", "名称": "上海·燃动!!高梨康治SUMMER LIVE TOUR IN CHINA 2024", "地点": "万代南梦宫上海文化中心", "具体时间范围": "2024-07-19 19:30:00", "最低票价": "280.0", "Link": "https://show.bilibili.com/platform/detail.html?id=87061", "Cover": "//i0.hdslb.com/bfs/openplatform/202406/H9TGguhL1717747212685.png"}, {"开始时间": "2024-07-20", "名称": "上海·BanG Dream！ONLY3", "地点": "交运智慧湾科创园25号楼", "具体时间范围": "2024-07-20 10:00:00", "最低票价": "78.0", "Link": "https://show.bilibili.com/platform/detail.html?id=87304", "Cover": "//i2.hdslb.com/bfs/openplatform/202406/wPmKJQDs1718182986843.jpeg"}, {"开始时间": "2024-07-20", "名称": "上海·创世次元动漫游戏嘉年华7.0", "地点": "七宝万科广场", "具体时间范围": "2024-07-20 10:00:00", "最低票价": "58.0", "Link": "https://show.bilibili.com/platform/detail.html?id=86344", "Cover": "//i1.hdslb.com/bfs/openplatform/202405/drK8Z2DU1716735561023.jpeg"}, {"开始时间": "2024-07-20", "名称": "上海·变形金刚交响音乐会40周年特别版", "地点": "捷豹上海交响音乐厅", "具体时间范围": "2024-07-20 19:30:00", "最低票价": "266.0", "Link": "https://show.bilibili.com/platform/detail.html?id=84261", "Cover": "//i1.hdslb.com/bfs/openplatform/202404/eqG3fTcX1713104706952.jpeg"}, {"开始时间": "2024-07-20 - 2024-07-21", "名称": "上海·LookLook动漫嘉年华2th", "地点": "上海国际短视频中心", "具体时间范围": "2024-07-20 10:00:00", "最低票价": "29.9", "Link": "https://show.bilibili.com/platform/detail.html?id=87169", "Cover": "//i0.hdslb.com/bfs/openplatform/202406/EGJoo1VF1718094234619.png"}, {"开始时间": "2024-07-20 - 2024-07-21", "名称": "上海·第九届Redamancy动漫游戏嘉年华", "地点": "上海环球港", "具体时间范围": "2024-07-20 10:00:00", "最低票价": "60.0", "Link": "https://show.bilibili.com/platform/detail.html?id=84637", "Cover": "//i1.hdslb.com/bfs/openplatform/202404/hWLkXqwM1713194236349.png"}, {"开始时间": "2024-07-21", "名称": "上海·Star2U跨次元嘉年华 vol.12.5～邦邦 Band Only～ ", "地点": "THE BOXX•城市乐园", "具体时间范围": "2024-07-21 14:00:00", "最低票价": "128.0", "Link": "https://show.bilibili.com/platform/detail.html?id=87110", "Cover": "//i1.hdslb.com/bfs/openplatform/202406/hL4TbuYJ1717762241867.jpeg"}, {"开始时间": "2024-07-21", "名称": "上海·藤川千爱2024演唱会", "地点": "万代南梦宫上海文化中心", "具体时间范围": "2024-07-21 16:00:00", "最低票价": "380.0", "Link": "https://show.bilibili.com/platform/detail.html?id=85360", "Cover": "//i0.hdslb.com/bfs/openplatform/202405/Qhk2XOza1715248510067.jpeg"}, {"开始时间": "2024-07-26", "名称": "上海·梁祝之父：何占豪指挥·《梁祝》65周年大型东方交响音乐会", "地点": "上海东方艺术中心音乐厅", "具体时间范围": "2024-07-26 19:30:00", "最低票价": "144.0", "Link": "https://show.bilibili.com/platform/detail.html?id=85591", "Cover": "//i2.hdslb.com/bfs/openplatform/202405/8bMGNbdd1715238003823.jpeg"}, {"开始时间": "2024-08-03", "名称": "上海·LOVELIVE ONLY", "地点": "JUMP工坊", "具体时间范围": "2024-08-03 14:00:00", "最低票价": "60.0", "Link": "https://show.bilibili.com/platform/detail.html?id=86711", "Cover": "//i2.hdslb.com/bfs/openplatform/202405/bllJHQFL1716983812432.jpeg"}, {"开始时间": "2024-08-03", "名称": "上海·《四月是你的谎言》——“公生”与“薰”的钢琴小提琴唯美经典音乐集", "地点": "上海东方艺术中心音乐厅", "具体时间范围": "2024-08-03 19:30:00", "最低票价": "80.0", "Link": "https://show.bilibili.com/platform/detail.html?id=84827", "Cover": "//i1.hdslb.com/bfs/openplatform/202404/hQBaZcog1714011608672.jpeg"}, {"开始时间": "2024-08-03", "名称": "上海·【大乐】《遇见梵高·星月夜》传世经典作品音乐会", "地点": "FANCL艺术中心", "具体时间范围": "2024-08-03 19:30:00", "最低票价": "40.0", "Link": "https://show.bilibili.com/platform/detail.html?id=85516", "Cover": "//i0.hdslb.com/bfs/openplatform/202405/iNr9uRU31715424434015.jpeg"}, {"开始时间": "2024-08-03", "名称": "上海·【神级现场】《冠位时之门：FUN肆二次元》——中华国乐·动漫ACG仲夏夜燃爆之巅", "地点": "加零剧场", "具体时间范围": "2024-08-03 19:30:00", "最低票价": "79.0", "Link": "https://show.bilibili.com/platform/detail.html?id=86821", "Cover": "//i2.hdslb.com/bfs/openplatform/202406/GT7aknBG1717571657329.jpeg"}, {"开始时间": "2024-08-03", "名称": "上海·【神级现场】《冠位时之门：青春回忆时廊》——中华国乐·二次元动漫ACG夏日清凉音乐会", "地点": "加零剧场", "具体时间范围": "2024-08-03 15:15:00", "最低票价": "128.0", "Link": "https://show.bilibili.com/platform/detail.html?id=86842", "Cover": "//i2.hdslb.com/bfs/openplatform/202406/heIkgSe71717657445122.jpeg"}, {"开始时间": "2024-08-04", "名称": "上海·赛马娘ONLY·星夜天航", "地点": "诺宝中心酒店", "具体时间范围": "2024-08-04 10:00:00", "最低票价": "80.0", "Link": "https://show.bilibili.com/platform/detail.html?id=87117", "Cover": "//i2.hdslb.com/bfs/openplatform/202406/bdPnwqoq1717659799773.jpeg"}, {"开始时间": "2024-08-10", "名称": "上海·创世次元动漫游戏嘉年华8.0", "地点": "七宝万科广场", "具体时间范围": "2024-08-10 10:00:00", "最低票价": "58.0", "Link": "https://show.bilibili.com/platform/detail.html?id=86337", "Cover": "//i1.hdslb.com/bfs/openplatform/202405/MryCBK6p1716736927373.jpeg"}, {"开始时间": "2024-08-11", "名称": "上海·KigOnly01·Kigurumi", "地点": "上海宝丰联大酒店", "具体时间范围": "2024-08-11 10:00:00", "最低票价": "不可售", "Link": "https://show.bilibili.com/platform/detail.html?id=85291", "Cover": "//i1.hdslb.com/bfs/openplatform/202404/GgqdW89w1714031044427.jpeg"}, {"开始时间": "2024-08-16", "名称": "上海·NANO 2024 演唱会  DO OR DIE!! Rock Your Heart Out", "地点": "万代南梦宫上海文化中心", "具体时间范围": "2024-08-16 19:30:00", "最低票价": "380.0", "Link": "https://show.bilibili.com/platform/detail.html?id=87165", "Cover": "//i0.hdslb.com/bfs/openplatform/202406/eVpEGaEI1718094225337.jpeg"}, {"开始时间": "2024-08-17", "名称": "上海·创世次元动漫游戏嘉年华9.0", "地点": "七宝万科广场", "具体时间范围": "2024-08-17 10:00:00", "最低票价": "58.0", "Link": "https://show.bilibili.com/platform/detail.html?id=86355", "Cover": "//i1.hdslb.com/bfs/openplatform/202405/UCMNMGbH1716782429997.jpeg"}, {"开始时间": "2024-08-17 - 2024-08-18", "名称": "上海·第六届燃梦BACG PRO动漫嘉年华-我们在燃梦相遇吧！", "地点": "万达汽车乐园(青浦万达茂店)", "具体时间范围": "2024-08-17 11:00:00", "最低票价": "65.8", "Link": "https://show.bilibili.com/platform/detail.html?id=85239", "Cover": "//i1.hdslb.com/bfs/openplatform/202405/mzD4rhY21715109458100.jpeg"}, {"开始时间": "2024-08-17 - 2024-08-25", "名称": "上海·音乐剧《消失的她》", "地点": "北外滩友邦大剧院", "具体时间范围": "2024-08-17 19:30:00", "最低票价": "480.0", "Link": "https://show.bilibili.com/platform/detail.html?id=86983", "Cover": "//i2.hdslb.com/bfs/openplatform/202406/Ks5A4X2i1717652089868.jpeg"}, {"开始时间": "2024-08-18", "名称": "上海·Marcin Patrzalek 2024 《原声之龙》指弹吉他音乐会", "地点": "万代南梦宫上海文化中心", "具体时间范围": "2024-08-18 19:30:00", "最低票价": "不可售", "Link": "https://show.bilibili.com/platform/detail.html?id=86297", "Cover": "//i1.hdslb.com/bfs/openplatform/202405/3y3sBaX31716548345650.jpeg"}, {"开始时间": "2024-08-24", "名称": "上海·幻梦游戏律动——怪物猎人X最终幻想X塞尔达 燃炸游戏室内乐音乐会", "地点": "上海商城剧院", "具体时间范围": "2024-08-24 19:30:00", "最低票价": "88.0", "Link": "https://show.bilibili.com/platform/detail.html?id=85461", "Cover": "//i2.hdslb.com/bfs/openplatform/202405/7fJJ5GxW1715327101441.jpeg"}, {"开始时间": "2024-09-08", "名称": "上海·【哥哥生日场，限量7折】“风继续吹”2024纪念张国荣金曲演唱会", "地点": "上海保利城市剧院", "具体时间范围": "2024-09-08 19:30:00", "最低票价": "128.0", "Link": "https://show.bilibili.com/platform/detail.html?id=87096", "Cover": "//i1.hdslb.com/bfs/openplatform/202406/ROl9e1Ko1717741374852.jpeg"}, {"开始时间": "2024-09-15 - 2024-09-16", "名称": "上海·第七届燃梦BACG PRO动漫嘉年华·我们在燃梦相遇吧！", "地点": "七宝万科广场", "具体时间范围": "2024-09-15 10:00:00", "最低票价": "58.0", "Link": "https://show.bilibili.com/platform/detail.html?id=85240", "Cover": "//i2.hdslb.com/bfs/openplatform/202405/RhRh4LZM1715110314459.jpeg"}, {"开始时间": "2024-09-20", "名称": "上海·魔弓传奇III“永恒的梁祝”——吕思清小提琴独奏音乐会", "地点": "北外滩友邦大剧院", "具体时间范围": "2024-09-20 19:30:00", "最低票价": "180.0", "Link": "https://show.bilibili.com/platform/detail.html?id=85044", "Cover": "//i0.hdslb.com/bfs/openplatform/202404/0z6hQm5B1714293642141.jpeg"}]}