{"展览": [{"开始时间": "2024-03-16", "名称": "合肥·CW国潮动漫游戏嘉年华", "地点": "南京路与庐州大道交汇处 合肥滨湖国际会展中心", "具体时间范围": "2024.03.16 09:30-03.17 17:00", "想去人数": 2960, "最低票价": 65, "Link": "https://show.bilibili.com/platform/detail.html?id=81284", "Cover": "//i0.hdslb.com/bfs/openplatform/202401/38B92fWF1705995243803.jpeg"}, {"开始时间": "2024-03-17", "名称": "合肥·CW国潮动漫游戏嘉年华-赵路内场", "地点": "南京路与庐州大道交汇处 合肥滨湖国际会展中心", "具体时间范围": "2024.03.17 09:00-03.17 17:00", "想去人数": 733, "最低票价": "已售罄", "Link": "https://show.bilibili.com/platform/detail.html?id=81954", "Cover": "//i0.hdslb.com/bfs/openplatform/202402/2PVn1ahm1708481741272.jpeg"}, {"开始时间": "2024-03-23", "名称": "合肥·原&铁&崩 only展", "地点": "金寨路与天堂窄路交叉口 梵木艺术中心", "具体时间范围": "2024.03.23 09:00-03.23 17:00", "想去人数": 103, "最低票价": 58, "Link": "https://show.bilibili.com/platform/detail.html?id=81574", "Cover": "//i2.hdslb.com/bfs/openplatform/202401/0V5uyX6C1706697212904.png"}, {"开始时间": "2024-04-04", "名称": "合肥· 第二届漫画城市动漫展 -故事再次开始", "地点": "凤淮路与固镇路西北角 庐阳全民健身中心", "具体时间范围": "2024.04.04 09:00-04.05 17:00", "想去人数": 6721, "最低票价": 60, "Link": "https://show.bilibili.com/platform/detail.html?id=78898", "Cover": "//i2.hdslb.com/bfs/openplatform/202402/3NgyB9761708333056023.jpeg"}, {"开始时间": "2024-04-04", "名称": "合肥·环形宇宙动漫游戏嘉年华", "地点": "南京路与庐州大道交汇处 合肥滨湖国际会展中心", "具体时间范围": "2024.04.04 09:30-04.05 17:00", "想去人数": 1697, "最低票价": "不可售", "Link": "https://show.bilibili.com/platform/detail.html?id=81916", "Cover": "//i0.hdslb.com/bfs/openplatform/202402/1lGzmBT61708336972816.jpeg"}, {"开始时间": "2024-04-04", "名称": "合肥·第二届漫画城市动漫展内场-柯暮卿", "地点": "凤淮路与固镇路西北角 庐阳全民健身中心", "具体时间范围": "2024.04.04 10:00-04.04 17:00", "想去人数": 21, "最低票价": 158, "Link": "https://show.bilibili.com/platform/detail.html?id=82192", "Cover": "//i0.hdslb.com/bfs/openplatform/202402/tcAAj9aj1709193127773.jpeg"}, {"开始时间": "2024-04-04", "名称": "合肥·第二届漫画城市动漫展内场-风袖", "地点": "凤淮路与固镇路西北角 庐阳全民健身中心", "具体时间范围": "2024.04.04 10:00-04.04 17:00", "想去人数": 31, "最低票价": 158, "Link": "https://show.bilibili.com/platform/detail.html?id=82191", "Cover": "//i2.hdslb.com/bfs/openplatform/202402/UZiEzBcc1709192469627.jpeg"}, {"开始时间": "2024-04-05", "名称": "合肥· 第二届漫画城市动漫展内场-《琅声雅集》", "地点": "凤淮路与固镇路西北角 庐阳全民健身中心", "具体时间范围": "2024.04.05 10:00-04.05 17:00", "想去人数": 57, "最低票价": 168, "Link": "https://show.bilibili.com/platform/detail.html?id=82189", "Cover": "//i0.hdslb.com/bfs/openplatform/202402/ZKkx4hTN1709191842946.jpeg"}, {"开始时间": "2024-04-21", "名称": "合肥·银魂only", "地点": "濉溪路118号 合肥栢景假日酒店", "具体时间范围": "2024.04.21 09:00-04.21 17:00", "想去人数": 117, "最低票价": 50, "Link": "https://show.bilibili.com/platform/detail.html?id=82145", "Cover": "//i1.hdslb.com/bfs/openplatform/202402/A0Tb5SQ51709091316985.jpeg"}, {"开始时间": "2024-05-03", "名称": "合肥·BH动漫游戏展", "地点": "科技园路与葡萄园路交口包河区现代农业示范园8号 圩乐田园生态营地", "具体时间范围": "2024.05.03 10:00-05.04 16:00", "想去人数": 24, "最低票价": 40, "Link": "https://show.bilibili.com/platform/detail.html?id=82199", "Cover": "//i0.hdslb.com/bfs/openplatform/202402/cSR2xlY61709195356978.jpeg"}, {"开始时间": "2024-05-18", "名称": "合肥·梦时空SPO1动漫展（取消）", "地点": "阜阳路16号 银瑞林国际大酒店", "具体时间范围": "2024.05.18 10:00-05.18 17:00", "想去人数": 131, "最低票价": "不可售", "Link": "https://show.bilibili.com/platform/detail.html?id=80207", "Cover": "//i2.hdslb.com/bfs/openplatform/202312/tQQOHYE01703574162111.jpeg"}], "演出": [], "本地生活": [], "全部类型": [{"开始时间": "2024-03-16", "名称": "合肥·CW国潮动漫游戏嘉年华", "地点": "南京路与庐州大道交汇处 合肥滨湖国际会展中心", "具体时间范围": "2024.03.16 09:30-03.17 17:00", "想去人数": 2960, "最低票价": 65, "Link": "https://show.bilibili.com/platform/detail.html?id=81284", "Cover": "//i0.hdslb.com/bfs/openplatform/202401/38B92fWF1705995243803.jpeg"}, {"开始时间": "2024-03-17", "名称": "合肥·CW国潮动漫游戏嘉年华-赵路内场", "地点": "南京路与庐州大道交汇处 合肥滨湖国际会展中心", "具体时间范围": "2024.03.17 09:00-03.17 17:00", "想去人数": 733, "最低票价": "已售罄", "Link": "https://show.bilibili.com/platform/detail.html?id=81954", "Cover": "//i0.hdslb.com/bfs/openplatform/202402/2PVn1ahm1708481741272.jpeg"}, {"开始时间": "2024-03-23", "名称": "合肥·原&铁&崩 only展", "地点": "金寨路与天堂窄路交叉口 梵木艺术中心", "具体时间范围": "2024.03.23 09:00-03.23 17:00", "想去人数": 103, "最低票价": 58, "Link": "https://show.bilibili.com/platform/detail.html?id=81574", "Cover": "//i2.hdslb.com/bfs/openplatform/202401/0V5uyX6C1706697212904.png"}, {"开始时间": "2024-04-04", "名称": "合肥· 第二届漫画城市动漫展 -故事再次开始", "地点": "凤淮路与固镇路西北角 庐阳全民健身中心", "具体时间范围": "2024.04.04 09:00-04.05 17:00", "想去人数": 6721, "最低票价": 60, "Link": "https://show.bilibili.com/platform/detail.html?id=78898", "Cover": "//i2.hdslb.com/bfs/openplatform/202402/3NgyB9761708333056023.jpeg"}, {"开始时间": "2024-04-04", "名称": "合肥·环形宇宙动漫游戏嘉年华", "地点": "南京路与庐州大道交汇处 合肥滨湖国际会展中心", "具体时间范围": "2024.04.04 09:30-04.05 17:00", "想去人数": 1697, "最低票价": "不可售", "Link": "https://show.bilibili.com/platform/detail.html?id=81916", "Cover": "//i0.hdslb.com/bfs/openplatform/202402/1lGzmBT61708336972816.jpeg"}, {"开始时间": "2024-04-04", "名称": "合肥·第二届漫画城市动漫展内场-柯暮卿", "地点": "凤淮路与固镇路西北角 庐阳全民健身中心", "具体时间范围": "2024.04.04 10:00-04.04 17:00", "想去人数": 21, "最低票价": 158, "Link": "https://show.bilibili.com/platform/detail.html?id=82192", "Cover": "//i0.hdslb.com/bfs/openplatform/202402/tcAAj9aj1709193127773.jpeg"}, {"开始时间": "2024-04-04", "名称": "合肥·第二届漫画城市动漫展内场-风袖", "地点": "凤淮路与固镇路西北角 庐阳全民健身中心", "具体时间范围": "2024.04.04 10:00-04.04 17:00", "想去人数": 31, "最低票价": 158, "Link": "https://show.bilibili.com/platform/detail.html?id=82191", "Cover": "//i2.hdslb.com/bfs/openplatform/202402/UZiEzBcc1709192469627.jpeg"}, {"开始时间": "2024-04-05", "名称": "合肥· 第二届漫画城市动漫展内场-《琅声雅集》", "地点": "凤淮路与固镇路西北角 庐阳全民健身中心", "具体时间范围": "2024.04.05 10:00-04.05 17:00", "想去人数": 57, "最低票价": 168, "Link": "https://show.bilibili.com/platform/detail.html?id=82189", "Cover": "//i0.hdslb.com/bfs/openplatform/202402/ZKkx4hTN1709191842946.jpeg"}, {"开始时间": "2024-04-21", "名称": "合肥·银魂only", "地点": "濉溪路118号 合肥栢景假日酒店", "具体时间范围": "2024.04.21 09:00-04.21 17:00", "想去人数": 117, "最低票价": 50, "Link": "https://show.bilibili.com/platform/detail.html?id=82145", "Cover": "//i1.hdslb.com/bfs/openplatform/202402/A0Tb5SQ51709091316985.jpeg"}, {"开始时间": "2024-05-03", "名称": "合肥·BH动漫游戏展", "地点": "科技园路与葡萄园路交口包河区现代农业示范园8号 圩乐田园生态营地", "具体时间范围": "2024.05.03 10:00-05.04 16:00", "想去人数": 24, "最低票价": 40, "Link": "https://show.bilibili.com/platform/detail.html?id=82199", "Cover": "//i0.hdslb.com/bfs/openplatform/202402/cSR2xlY61709195356978.jpeg"}, {"开始时间": "2024-05-18", "名称": "合肥·梦时空SPO1动漫展（取消）", "地点": "阜阳路16号 银瑞林国际大酒店", "具体时间范围": "2024.05.18 10:00-05.18 17:00", "想去人数": 131, "最低票价": "不可售", "Link": "https://show.bilibili.com/platform/detail.html?id=80207", "Cover": "//i2.hdslb.com/bfs/openplatform/202312/tQQOHYE01703574162111.jpeg"}]}