{"展览": [{"开始时间": "2024-05-25", "名称": "合肥·第五人格ONLY", "地点": "合肥方圆荟(滨湖店)", "具体时间范围": "2024-05-25 10:00:00", "最低票价": "65.0", "Link": "https://show.bilibili.com/platform/detail.html?id=85262", "Cover": "//i2.hdslb.com/bfs/openplatform/202405/lc7GHvuy1715083676422.jpeg"}, {"开始时间": "2024-06-01", "名称": "合肥·TH元气动漫游戏嘉年华", "地点": "曙光薇酒店(合肥站店)", "具体时间范围": "2024-06-01 10:00:00", "最低票价": "50.0", "Link": "https://show.bilibili.com/platform/detail.html?id=85181", "Cover": "//i0.hdslb.com/bfs/openplatform/202405/QcP0IlNZ1715064886624.jpeg"}, {"开始时间": "2024-06-01", "名称": "合肥·运动番only·群青日和", "地点": "合肥明星运动公园", "具体时间范围": "2024-06-01 09:30:00", "最低票价": "70.0", "Link": "https://show.bilibili.com/platform/detail.html?id=83058", "Cover": "//i2.hdslb.com/bfs/openplatform/202404/Jzeq47lD1714026878824.jpeg"}, {"开始时间": "2024-06-08 - 2024-06-09", "名称": "合肥·第六届环形宇宙动漫游戏嘉年华-一周年超强巨制~", "地点": "合肥滨湖会展中心", "具体时间范围": "2024-06-08 09:30:00", "最低票价": "65.0", "Link": "https://show.bilibili.com/platform/detail.html?id=83518", "Cover": "//i1.hdslb.com/bfs/openplatform/202403/1Sqp42gM1711691520194.jpeg"}, {"开始时间": "2024-06-08 - 2024-06-10", "名称": "合肥·FT动漫嘉年华（免费）", "地点": "肥西旭辉Cmall", "具体时间范围": "2024-06-08 10:30:00", "最低票价": "25.0", "Link": "https://show.bilibili.com/platform/detail.html?id=85438", "Cover": "//i1.hdslb.com/bfs/openplatform/202405/5V9yXbFR1715334292430.jpeg"}, {"开始时间": "2024-06-09", "名称": "合肥·第六届环形宇宙动漫游戏嘉年华内场票·赵成晨", "地点": "合肥滨湖国际会展中心", "具体时间范围": "2024-06-09 09:30:00", "最低票价": "已售罄", "Link": "https://show.bilibili.com/platform/detail.html?id=84863", "Cover": "//i1.hdslb.com/bfs/openplatform/202404/I5S4Ih2M1714031127805.jpeg"}, {"开始时间": "2024-06-09 - 2024-06-10", "名称": "合肥·第二届华盟动漫次元嘉年华", "地点": "合肥当代美术馆", "具体时间范围": "2024-06-09 10:00:00", "最低票价": "58.0", "Link": "https://show.bilibili.com/platform/detail.html?id=84081", "Cover": "//i1.hdslb.com/bfs/openplatform/202404/O5LyHE7j1712732240786.jpeg"}, {"开始时间": "2024-06-22", "名称": "合肥·Look Look动漫嘉年华", "地点": "少荃体育中心", "具体时间范围": "2024-06-22 10:00:00", "最低票价": "58.0", "Link": "https://show.bilibili.com/platform/detail.html?id=82311", "Cover": "//i2.hdslb.com/bfs/openplatform/202404/RFYwkzvt1713951750482.jpeg"}, {"开始时间": "2024-06-22 - 2024-06-23", "名称": "合肥·城市动漫节", "地点": "大机库演艺中心", "具体时间范围": "2024-06-22 10:00:00", "最低票价": "50.0", "Link": "https://show.bilibili.com/platform/detail.html?id=85000", "Cover": "//i2.hdslb.com/bfs/openplatform/202404/U2EZscfQ1714448575403.jpeg"}, {"开始时间": "2024-06-30", "名称": "合肥·第1.5届星芒动漫嘉年华", "地点": "挥动体育", "具体时间范围": "2024-06-30 09:30:00", "最低票价": "60.0", "Link": "https://show.bilibili.com/platform/detail.html?id=85213", "Cover": "//i1.hdslb.com/bfs/openplatform/202405/v40vLtJl1715073148563.jpeg"}, {"开始时间": "2024-06-30", "名称": "安徽·THO4·隙间皖韵之梦", "地点": "蓝金湾大酒店", "具体时间范围": "2024-06-30 10:00:00", "最低票价": "65.0", "Link": "https://show.bilibili.com/platform/detail.html?id=85119", "Cover": "//i2.hdslb.com/bfs/openplatform/202405/kuuarwvJ1714932457216.jpeg"}, {"开始时间": "2024-07-14", "名称": "合肥·第一届宅舞比赛漫展-CF01", "地点": "合肥银泰君亭酒店", "具体时间范围": "2024-07-14 10:00:00", "最低票价": "59.0", "Link": "https://show.bilibili.com/platform/detail.html?id=85544", "Cover": "//i2.hdslb.com/bfs/openplatform/202405/sDlSCXnC1715316021248.jpeg"}, {"开始时间": "2024-07-20", "名称": "合肥·W·A首届童年怀旧only", "地点": "格律诗婚礼艺术中心(新站店)", "具体时间范围": "2024-07-20 09:30:00", "最低票价": "78.0", "Link": "https://show.bilibili.com/platform/detail.html?id=84794", "Cover": "//i2.hdslb.com/bfs/openplatform/202404/Ie0KTNEr1713951888990.png"}, {"开始时间": "2024-07-20", "名称": "安徽·赛马娘Only 2.0", "地点": "赫拉诺言艺术中心", "具体时间范围": "2024-07-20 09:00:00", "最低票价": "78.0", "Link": "https://show.bilibili.com/platform/detail.html?id=84539", "Cover": "//i1.hdslb.com/bfs/openplatform/202405/ibcY9Edj1715235810905.jpeg"}, {"开始时间": "2024-07-20 - 2024-07-21", "名称": "合肥·第十四届次元之门动漫游戏博览会", "地点": "合肥滨湖国际会展中心", "具体时间范围": "2024-07-20 10:00:00", "最低票价": "68.0", "Link": "https://show.bilibili.com/platform/detail.html?id=85336", "Cover": "//i2.hdslb.com/bfs/openplatform/202405/Bu6iQPJ01715161445356.jpeg"}, {"开始时间": "2024-07-27", "名称": "安徽·MAX特摄only展", "地点": "赤阑桥艺术空间", "具体时间范围": "2024-07-27 09:30:00", "最低票价": "50.0", "Link": "https://show.bilibili.com/platform/detail.html?id=83684", "Cover": "//i0.hdslb.com/bfs/openplatform/202405/qBnW1VeB1715423018997.jpeg"}, {"开始时间": "2024-08-03 - 2024-08-04", "名称": "合肥·第七届环形宇宙动漫游戏嘉年华", "地点": "合肥滨湖国际会展中心", "具体时间范围": "2024-08-03 09:30:00", "最低票价": "49.0", "Link": "https://show.bilibili.com/platform/detail.html?id=84767", "Cover": "//i2.hdslb.com/bfs/openplatform/202404/nBGuQecO1713856894035.jpeg"}], "演出": [{"开始时间": "2024-06-01", "名称": "合肥·跨越二次元ACG神级动漫世界巡回演唱会", "地点": "合肥九莱福", "具体时间范围": "2024-06-01 20:00:00", "最低票价": 138.0, "Link": "https://show.bilibili.com/platform/detail.html?id=85179", "Cover": "//i1.hdslb.com/bfs/openplatform/202405/S1x6SBNF1714972333798.jpeg"}, {"开始时间": "2024-08-03", "名称": "合肥·首届包河留声机音乐节—《菊次郎的夏天》久石让钢琴曲梦幻之旅演奏会", "地点": "包河凤凰剧院", "具体时间范围": "2024-08-03 19:30:00", "最低票价": 80.0, "Link": "https://show.bilibili.com/platform/detail.html?id=83556", "Cover": "//i1.hdslb.com/bfs/openplatform/202403/4nwOTVDu1711695345941.jpeg"}], "本地生活": [], "全部类型": [{"开始时间": "2024-05-25", "名称": "合肥·第五人格ONLY", "地点": "合肥方圆荟(滨湖店)", "具体时间范围": "2024-05-25 10:00:00", "最低票价": "65.0", "Link": "https://show.bilibili.com/platform/detail.html?id=85262", "Cover": "//i2.hdslb.com/bfs/openplatform/202405/lc7GHvuy1715083676422.jpeg"}, {"开始时间": "2024-06-01", "名称": "合肥·TH元气动漫游戏嘉年华", "地点": "曙光薇酒店(合肥站店)", "具体时间范围": "2024-06-01 10:00:00", "最低票价": "50.0", "Link": "https://show.bilibili.com/platform/detail.html?id=85181", "Cover": "//i0.hdslb.com/bfs/openplatform/202405/QcP0IlNZ1715064886624.jpeg"}, {"开始时间": "2024-06-01", "名称": "合肥·跨越二次元ACG神级动漫世界巡回演唱会", "地点": "合肥九莱福", "具体时间范围": "2024-06-01 20:00:00", "最低票价": "138.0", "Link": "https://show.bilibili.com/platform/detail.html?id=85179", "Cover": "//i1.hdslb.com/bfs/openplatform/202405/S1x6SBNF1714972333798.jpeg"}, {"开始时间": "2024-06-01", "名称": "合肥·运动番only·群青日和", "地点": "合肥明星运动公园", "具体时间范围": "2024-06-01 09:30:00", "最低票价": "70.0", "Link": "https://show.bilibili.com/platform/detail.html?id=83058", "Cover": "//i2.hdslb.com/bfs/openplatform/202404/Jzeq47lD1714026878824.jpeg"}, {"开始时间": "2024-06-08 - 2024-06-09", "名称": "合肥·第六届环形宇宙动漫游戏嘉年华-一周年超强巨制~", "地点": "合肥滨湖会展中心", "具体时间范围": "2024-06-08 09:30:00", "最低票价": "65.0", "Link": "https://show.bilibili.com/platform/detail.html?id=83518", "Cover": "//i1.hdslb.com/bfs/openplatform/202403/1Sqp42gM1711691520194.jpeg"}, {"开始时间": "2024-06-08 - 2024-06-10", "名称": "合肥·FT动漫嘉年华（免费）", "地点": "肥西旭辉Cmall", "具体时间范围": "2024-06-08 10:30:00", "最低票价": "25.0", "Link": "https://show.bilibili.com/platform/detail.html?id=85438", "Cover": "//i1.hdslb.com/bfs/openplatform/202405/5V9yXbFR1715334292430.jpeg"}, {"开始时间": "2024-06-09", "名称": "合肥·第六届环形宇宙动漫游戏嘉年华内场票·赵成晨", "地点": "合肥滨湖国际会展中心", "具体时间范围": "2024-06-09 09:30:00", "最低票价": "已售罄", "Link": "https://show.bilibili.com/platform/detail.html?id=84863", "Cover": "//i1.hdslb.com/bfs/openplatform/202404/I5S4Ih2M1714031127805.jpeg"}, {"开始时间": "2024-06-09 - 2024-06-10", "名称": "合肥·第二届华盟动漫次元嘉年华", "地点": "合肥当代美术馆", "具体时间范围": "2024-06-09 10:00:00", "最低票价": "58.0", "Link": "https://show.bilibili.com/platform/detail.html?id=84081", "Cover": "//i1.hdslb.com/bfs/openplatform/202404/O5LyHE7j1712732240786.jpeg"}, {"开始时间": "2024-06-22", "名称": "合肥·Look Look动漫嘉年华", "地点": "少荃体育中心", "具体时间范围": "2024-06-22 10:00:00", "最低票价": "58.0", "Link": "https://show.bilibili.com/platform/detail.html?id=82311", "Cover": "//i2.hdslb.com/bfs/openplatform/202404/RFYwkzvt1713951750482.jpeg"}, {"开始时间": "2024-06-22 - 2024-06-23", "名称": "合肥·城市动漫节", "地点": "大机库演艺中心", "具体时间范围": "2024-06-22 10:00:00", "最低票价": "50.0", "Link": "https://show.bilibili.com/platform/detail.html?id=85000", "Cover": "//i2.hdslb.com/bfs/openplatform/202404/U2EZscfQ1714448575403.jpeg"}, {"开始时间": "2024-06-30", "名称": "合肥·第1.5届星芒动漫嘉年华", "地点": "挥动体育", "具体时间范围": "2024-06-30 09:30:00", "最低票价": "60.0", "Link": "https://show.bilibili.com/platform/detail.html?id=85213", "Cover": "//i1.hdslb.com/bfs/openplatform/202405/v40vLtJl1715073148563.jpeg"}, {"开始时间": "2024-06-30", "名称": "安徽·THO4·隙间皖韵之梦", "地点": "蓝金湾大酒店", "具体时间范围": "2024-06-30 10:00:00", "最低票价": "65.0", "Link": "https://show.bilibili.com/platform/detail.html?id=85119", "Cover": "//i2.hdslb.com/bfs/openplatform/202405/kuuarwvJ1714932457216.jpeg"}, {"开始时间": "2024-07-14", "名称": "合肥·第一届宅舞比赛漫展-CF01", "地点": "合肥银泰君亭酒店", "具体时间范围": "2024-07-14 10:00:00", "最低票价": "59.0", "Link": "https://show.bilibili.com/platform/detail.html?id=85544", "Cover": "//i2.hdslb.com/bfs/openplatform/202405/sDlSCXnC1715316021248.jpeg"}, {"开始时间": "2024-07-20", "名称": "合肥·W·A首届童年怀旧only", "地点": "格律诗婚礼艺术中心(新站店)", "具体时间范围": "2024-07-20 09:30:00", "最低票价": "78.0", "Link": "https://show.bilibili.com/platform/detail.html?id=84794", "Cover": "//i2.hdslb.com/bfs/openplatform/202404/Ie0KTNEr1713951888990.png"}, {"开始时间": "2024-07-20", "名称": "安徽·赛马娘Only 2.0", "地点": "赫拉诺言艺术中心", "具体时间范围": "2024-07-20 09:00:00", "最低票价": "78.0", "Link": "https://show.bilibili.com/platform/detail.html?id=84539", "Cover": "//i1.hdslb.com/bfs/openplatform/202405/ibcY9Edj1715235810905.jpeg"}, {"开始时间": "2024-07-20 - 2024-07-21", "名称": "合肥·第十四届次元之门动漫游戏博览会", "地点": "合肥滨湖国际会展中心", "具体时间范围": "2024-07-20 10:00:00", "最低票价": "68.0", "Link": "https://show.bilibili.com/platform/detail.html?id=85336", "Cover": "//i2.hdslb.com/bfs/openplatform/202405/Bu6iQPJ01715161445356.jpeg"}, {"开始时间": "2024-07-27", "名称": "安徽·MAX特摄only展", "地点": "赤阑桥艺术空间", "具体时间范围": "2024-07-27 09:30:00", "最低票价": "50.0", "Link": "https://show.bilibili.com/platform/detail.html?id=83684", "Cover": "//i0.hdslb.com/bfs/openplatform/202405/qBnW1VeB1715423018997.jpeg"}, {"开始时间": "2024-08-03", "名称": "合肥·首届包河留声机音乐节—《菊次郎的夏天》久石让钢琴曲梦幻之旅演奏会", "地点": "包河凤凰剧院", "具体时间范围": "2024-08-03 19:30:00", "最低票价": "80.0", "Link": "https://show.bilibili.com/platform/detail.html?id=83556", "Cover": "//i1.hdslb.com/bfs/openplatform/202403/4nwOTVDu1711695345941.jpeg"}, {"开始时间": "2024-08-03 - 2024-08-04", "名称": "合肥·第七届环形宇宙动漫游戏嘉年华", "地点": "合肥滨湖国际会展中心", "具体时间范围": "2024-08-03 09:30:00", "最低票价": "49.0", "Link": "https://show.bilibili.com/platform/detail.html?id=84767", "Cover": "//i2.hdslb.com/bfs/openplatform/202404/nBGuQecO1713856894035.jpeg"}]}